{
    "domain": "bdxiguaimg.com",
    "owner": {},
    "source": [
        "DuckDuckGo-US"
    ],
    "prevalence": 0.0000135,
    "sites": 2,
    "subdomains": [
        "p3-sign",
        "p26-sign",
        "p6-sign"
    ],
    "cnames": [],
    "fingerprinting": 0,
    "resources": [
        {
            "rule": "bdxiguaimg\\.com\\/tos-cn-i-0004\\/5a223da106394f37a2282b4eb7d49aae~tplv-pk90l89vgd-crop-center:864:486\\.avif",
            "cookies": 0,
            "fingerprinting": 0,
            "subdomains": [
                "p3-sign"
            ],
            "apis": {},
            "sites": 2,
            "prevalence": 0.0000135,
            "cnames": [],
            "responseHashes": [
                "5a5295e05cb26b23ca6002162ec6e5dc9acee79b3decefcb450ab667a500ccb5"
            ],
            "type": "Image",
            "firstPartyCookies": {},
            "firstPartyCookiesSent": {},
            "exampleSites": [
                "ixigua.com",
                "www.ixigua.com"
            ]
        },
        {
            "rule": "bdxiguaimg\\.com\\/tos-cn-i-0026\\/b44f98d46a9741bd8d0b5ed8d88c592f~tplv-pk90l89vgd-crop-center:864:486\\.avif",
            "cookies": 0,
            "fingerprinting": 0,
            "subdomains": [
                "p3-sign"
            ],
            "apis": {},
            "sites": 2,
            "prevalence": 0.0000135,
            "cnames": [],
            "responseHashes": [
                "f181e73414ccc0f532453c1f1729982fb32655f371b786c8632fa6c5a3b01d3b"
            ],
            "type": "Image",
            "firstPartyCookies": {},
            "firstPartyCookiesSent": {},
            "exampleSites": [
                "ixigua.com",
                "www.ixigua.com"
            ]
        },
        {
            "rule": "bdxiguaimg\\.com\\/tos-cn-i-0026\\/0194317d19484e8b89948af761f965a0~tplv-pk90l89vgd-crop-center:864:486\\.avif",
            "cookies": 0,
            "fingerprinting": 0,
            "subdomains": [
                "p3-sign"
            ],
            "apis": {},
            "sites": 2,
            "prevalence": 0.0000135,
            "cnames": [],
            "responseHashes": [
                "b6adb4fdb55e92819bdaf8282967b37262d63cc60c78461a1b31f54b82a55241"
            ],
            "type": "Image",
            "firstPartyCookies": {},
            "firstPartyCookiesSent": {},
            "exampleSites": [
                "ixigua.com",
                "www.ixigua.com"
            ]
        },
        {
            "rule": "bdxiguaimg\\.com\\/tos-cn-i-0004\\/871df8549818403a9623b9fe7cfee321~tplv-pk90l89vgd-crop-center:864:486\\.avif",
            "cookies": 0,
            "fingerprinting": 0,
            "subdomains": [
                "p26-sign"
            ],
            "apis": {},
            "sites": 2,
            "prevalence": 0.0000135,
            "cnames": [],
            "responseHashes": [
                "5c45732dc3aadb8ce62a366b168b021f356ca6dc175aa292b23c23bd8e75c23c"
            ],
            "type": "Image",
            "firstPartyCookies": {},
            "firstPartyCookiesSent": {},
            "exampleSites": [
                "ixigua.com",
                "www.ixigua.com"
            ]
        },
        {
            "rule": "bdxiguaimg\\.com\\/tos-cn-i-0004\\/83aa3844c0b24de0ac29ffa539c1c5ee~tplv-pk90l89vgd-crop-center:864:486\\.avif",
            "cookies": 0,
            "fingerprinting": 0,
            "subdomains": [
                "p6-sign"
            ],
            "apis": {},
            "sites": 2,
            "prevalence": 0.0000135,
            "cnames": [],
            "responseHashes": [
                "3aea52c93ec4af18751a0c65ff03f76562447457f3c9f5fdaf0f8ca72c0d3e6b"
            ],
            "type": "Image",
            "firstPartyCookies": {},
            "firstPartyCookiesSent": {},
            "exampleSites": [
                "ixigua.com",
                "www.ixigua.com"
            ]
        },
        {
            "rule": "bdxiguaimg\\.com\\/tos-cn-i-0026\\/26f83bb3105a4c019365e10062f24fde~tplv-pk90l89vgd-crop-center:864:486\\.avif",
            "cookies": 0,
            "fingerprinting": 0,
            "subdomains": [
                "p6-sign"
            ],
            "apis": {},
            "sites": 2,
            "prevalence": 0.0000135,
            "cnames": [],
            "responseHashes": [
                "87af2b117074ed4e9b3e9504ae2454165c4d79e5b40ea856f26bf17b5070dc1e"
            ],
            "type": "Image",
            "firstPartyCookies": {},
            "firstPartyCookiesSent": {},
            "exampleSites": [
                "ixigua.com",
                "www.ixigua.com"
            ]
        },
        {
            "rule": "bdxiguaimg\\.com\\/tos-cn-i-0004\\/c496db7a38bf4cd7b7ef2de20fb37f29~tplv-pk90l89vgd-crop-center:864:486\\.avif",
            "cookies": 0,
            "fingerprinting": 0,
            "subdomains": [
                "p26-sign"
            ],
            "apis": {},
            "sites": 2,
            "prevalence": 0.0000135,
            "cnames": [],
            "responseHashes": [
                "24999830c0bdfa2513257800f0123388b9afe42a7af7d744b23a331a0f9f4222"
            ],
            "type": "Image",
            "firstPartyCookies": {},
            "firstPartyCookiesSent": {},
            "exampleSites": [
                "ixigua.com",
                "www.ixigua.com"
            ]
        },
        {
            "rule": "bdxiguaimg\\.com\\/tos-cn-i-0026\\/cfd03eeb76a440538d7b98e3c519c46b~tplv-pk90l89vgd-crop-center:864:486\\.avif",
            "cookies": 0,
            "fingerprinting": 0,
            "subdomains": [
                "p26-sign"
            ],
            "apis": {},
            "sites": 2,
            "prevalence": 0.0000135,
            "cnames": [],
            "responseHashes": [
                "a948b33cdbe71b4d8e74a1652900766364946a15cbaf48754fe066ab8946c440"
            ],
            "type": "Image",
            "firstPartyCookies": {},
            "firstPartyCookiesSent": {},
            "exampleSites": [
                "ixigua.com",
                "www.ixigua.com"
            ]
        },
        {
            "rule": "bdxiguaimg\\.com\\/tos-cn-i-0004\\/202c74a774cc4fea88ba64b8966cd4eb~tplv-pk90l89vgd-crop-center:864:486\\.avif",
            "cookies": 0,
            "fingerprinting": 0,
            "subdomains": [
                "p6-sign"
            ],
            "apis": {},
            "sites": 2,
            "prevalence": 0.0000135,
            "cnames": [],
            "responseHashes": [
                "71c6e5bcf017d64139ae65d652b5a6bb593bcbcd47b7d407602e0b9cf39fe8e2"
            ],
            "type": "Image",
            "firstPartyCookies": {},
            "firstPartyCookiesSent": {},
            "exampleSites": [
                "ixigua.com",
                "www.ixigua.com"
            ]
        },
        {
            "rule": "bdxiguaimg\\.com\\/tos-cn-i-0026\\/3ece33f694ad4c67a84203ca8fc3af82~tplv-pk90l89vgd-crop-center:864:486\\.avif",
            "cookies": 0,
            "fingerprinting": 0,
            "subdomains": [
                "p6-sign"
            ],
            "apis": {},
            "sites": 2,
            "prevalence": 0.0000135,
            "cnames": [],
            "responseHashes": [
                "7259df31c1267a614d2f056ccbedaedc79e337ed5714e13d7be6c9b01e80282a"
            ],
            "type": "Image",
            "firstPartyCookies": {},
            "firstPartyCookiesSent": {},
            "exampleSites": [
                "ixigua.com",
                "www.ixigua.com"
            ]
        },
        {
            "rule": "bdxiguaimg\\.com\\/tos-cn-i-0026\\/c061599b1061456cb8bf50639455e861~tplv-pk90l89vgd-crop-center:864:486\\.avif",
            "cookies": 0,
            "fingerprinting": 0,
            "subdomains": [
                "p6-sign"
            ],
            "apis": {},
            "sites": 2,
            "prevalence": 0.0000135,
            "cnames": [],
            "responseHashes": [
                "5655d6020086a52f1e12e4e1e0e8cd22a736aeed4ba7a8a546088c3ed88bb1e2"
            ],
            "type": "Image",
            "firstPartyCookies": {},
            "firstPartyCookiesSent": {},
            "exampleSites": [
                "ixigua.com",
                "www.ixigua.com"
            ]
        },
        {
            "rule": "bdxiguaimg\\.com\\/tos-cn-i-0026\\/df34a132be5e47a18a7070a351cc63d4~tplv-pk90l89vgd-crop-center:864:486\\.avif",
            "cookies": 0,
            "fingerprinting": 0,
            "subdomains": [
                "p6-sign"
            ],
            "apis": {},
            "sites": 2,
            "prevalence": 0.0000135,
            "cnames": [],
            "responseHashes": [
                "a429b633196e69892ee90592548053989c95a867e432bf0355fd10144f824848"
            ],
            "type": "Image",
            "firstPartyCookies": {},
            "firstPartyCookiesSent": {},
            "exampleSites": [
                "ixigua.com",
                "www.ixigua.com"
            ]
        },
        {
            "rule": "bdxiguaimg\\.com\\/tos-cn-p-0015\\/18db093aa154440bb167a2ac7d9e60fe~tplv-pk90l89vgd-crop-center:864:486\\.avif",
            "cookies": 0,
            "fingerprinting": 0,
            "subdomains": [
                "p26-sign"
            ],
            "apis": {},
            "sites": 2,
            "prevalence": 0.0000135,
            "cnames": [],
            "responseHashes": [
                "4e5c336be1592d29f9665a29f8bad26c8aa326bd189dc694d0a41a4e810c21e0"
            ],
            "type": "Image",
            "firstPartyCookies": {},
            "firstPartyCookiesSent": {},
            "exampleSites": [
                "ixigua.com",
                "www.ixigua.com"
            ]
        },
        {
            "rule": "bdxiguaimg\\.com\\/tos-cn-i-0004\\/85f1d9099f24441dab6dfb1aa62f04fb~tplv-pk90l89vgd-crop-center:864:486\\.avif",
            "cookies": 0,
            "fingerprinting": 0,
            "subdomains": [
                "p6-sign"
            ],
            "apis": {},
            "sites": 2,
            "prevalence": 0.0000135,
            "cnames": [],
            "responseHashes": [
                "d6878fc22b864738a7d33a752ecc306b3ecb174448f3473fd823e85ea6f08b29"
            ],
            "type": "Image",
            "firstPartyCookies": {},
            "firstPartyCookiesSent": {},
            "exampleSites": [
                "ixigua.com",
                "www.ixigua.com"
            ]
        },
        {
            "rule": "bdxiguaimg\\.com\\/tos-cn-i-0026\\/b1b010975e2e481c8b3744761d99759d~tplv-pk90l89vgd-crop-center:864:486\\.avif",
            "cookies": 0,
            "fingerprinting": 0,
            "subdomains": [
                "p26-sign"
            ],
            "apis": {},
            "sites": 2,
            "prevalence": 0.0000135,
            "cnames": [],
            "responseHashes": [
                "fef9bcbc6d375f1965f775cb47bd21a564693014e6923539f69fc23c51e4381a"
            ],
            "type": "Image",
            "firstPartyCookies": {},
            "firstPartyCookiesSent": {},
            "exampleSites": [
                "ixigua.com",
                "www.ixigua.com"
            ]
        },
        {
            "rule": "bdxiguaimg\\.com\\/tos-cn-p-0015\\/0c5a50aade13441885f0727a2048f2df~tplv-pk90l89vgd-crop-center:864:486\\.avif",
            "cookies": 0,
            "fingerprinting": 0,
            "subdomains": [
                "p26-sign"
            ],
            "apis": {},
            "sites": 2,
            "prevalence": 0.0000135,
            "cnames": [],
            "responseHashes": [
                "4c0674d967f9cabc9cc01c6cc66feac78604405c9174e07dbc3245cfe4a43bcf"
            ],
            "type": "Image",
            "firstPartyCookies": {},
            "firstPartyCookiesSent": {},
            "exampleSites": [
                "ixigua.com",
                "www.ixigua.com"
            ]
        },
        {
            "rule": "bdxiguaimg\\.com\\/tos-cn-i-0026\\/0dbf28b78c0d4f8bba483d9536781c39~tplv-pk90l89vgd-crop-center:864:486\\.avif",
            "cookies": 0,
            "fingerprinting": 0,
            "subdomains": [
                "p3-sign"
            ],
            "apis": {},
            "sites": 2,
            "prevalence": 0.0000135,
            "cnames": [],
            "responseHashes": [
                "3db7fd4344b91c09e261e274fab4e296eab6a5aef67b3714a9dd822cd6eda2c2"
            ],
            "type": "Image",
            "firstPartyCookies": {},
            "firstPartyCookiesSent": {},
            "exampleSites": [
                "ixigua.com",
                "www.ixigua.com"
            ]
        },
        {
            "rule": "bdxiguaimg\\.com\\/tos-cn-i-0026\\/a8bd426f367848a7aa1c5754bdbdccca~tplv-pk90l89vgd-crop-center:864:486\\.avif",
            "cookies": 0,
            "fingerprinting": 0,
            "subdomains": [
                "p6-sign"
            ],
            "apis": {},
            "sites": 2,
            "prevalence": 0.0000135,
            "cnames": [],
            "responseHashes": [
                "f6e94e02a3ee2f8bbb018a3c62a638b38292be6509959d95ec841ba72b4d1fab"
            ],
            "type": "Image",
            "firstPartyCookies": {},
            "firstPartyCookiesSent": {},
            "exampleSites": [
                "ixigua.com",
                "www.ixigua.com"
            ]
        },
        {
            "rule": "bdxiguaimg\\.com\\/tos-cn-i-0004\\/d952e936935b4558886da119ca008107~tplv-pk90l89vgd-crop-center:864:486\\.avif",
            "cookies": 0,
            "fingerprinting": 0,
            "subdomains": [
                "p3-sign"
            ],
            "apis": {},
            "sites": 2,
            "prevalence": 0.0000135,
            "cnames": [],
            "responseHashes": [
                "5f1332594b73793a84e8023063cd1cf26f94851cce36945a2729dc632905f51d"
            ],
            "type": "Image",
            "firstPartyCookies": {},
            "firstPartyCookiesSent": {},
            "exampleSites": [
                "ixigua.com",
                "www.ixigua.com"
            ]
        },
        {
            "rule": "bdxiguaimg\\.com\\/tos-cn-i-0004\\/f948d95a6a7e4595bb224ee02f37b082~tplv-pk90l89vgd-crop-center:864:486\\.avif",
            "cookies": 0,
            "fingerprinting": 0,
            "subdomains": [
                "p6-sign"
            ],
            "apis": {},
            "sites": 2,
            "prevalence": 0.0000135,
            "cnames": [],
            "responseHashes": [
                "2559c3263e46205e4e0cc970fc17ea532a3587c854ec64d0fee8c523e763140c"
            ],
            "type": "Image",
            "firstPartyCookies": {},
            "firstPartyCookiesSent": {},
            "exampleSites": [
                "ixigua.com",
                "www.ixigua.com"
            ]
        },
        {
            "rule": "bdxiguaimg\\.com\\/tos-cn-i-0026\\/4c71056694474ac08791894c2ef3c20f~tplv-pk90l89vgd-crop-center:864:486\\.avif",
            "cookies": 0,
            "fingerprinting": 0,
            "subdomains": [
                "p26-sign"
            ],
            "apis": {},
            "sites": 2,
            "prevalence": 0.0000135,
            "cnames": [],
            "responseHashes": [
                "b061712269be5167b0b168d23c70779e49fb0d86d1b7194631bab5ab55f27771"
            ],
            "type": "Image",
            "firstPartyCookies": {},
            "firstPartyCookiesSent": {},
            "exampleSites": [
                "ixigua.com",
                "www.ixigua.com"
            ]
        },
        {
            "rule": "bdxiguaimg\\.com\\/tos-cn-i-0026\\/f77ed3c6e7cf4237857f05279f6f6260~tplv-pk90l89vgd-crop-center:864:486\\.avif",
            "cookies": 0,
            "fingerprinting": 0,
            "subdomains": [
                "p3-sign"
            ],
            "apis": {},
            "sites": 2,
            "prevalence": 0.0000135,
            "cnames": [],
            "responseHashes": [
                "ebb943e7f29f5b809887e12a0f582ee078d81889626c7914b50658b70d90af05"
            ],
            "type": "Image",
            "firstPartyCookies": {},
            "firstPartyCookiesSent": {},
            "exampleSites": [
                "ixigua.com",
                "www.ixigua.com"
            ]
        },
        {
            "rule": "bdxiguaimg\\.com\\/tos-cn-i-0026\\/34d9353f27a340088450b1e36ec07a44~tplv-pk90l89vgd-crop-center:864:486\\.avif",
            "cookies": 0,
            "fingerprinting": 0,
            "subdomains": [
                "p6-sign"
            ],
            "apis": {},
            "sites": 2,
            "prevalence": 0.0000135,
            "cnames": [],
            "responseHashes": [
                "97a6887ea07b96de6b1a3bae62aeabc9d2b2dcf146a4fb71c06aa040939c40d6"
            ],
            "type": "Image",
            "firstPartyCookies": {},
            "firstPartyCookiesSent": {},
            "exampleSites": [
                "ixigua.com",
                "www.ixigua.com"
            ]
        },
        {
            "rule": "bdxiguaimg\\.com\\/tos-cn-i-0004\\/5e82bb05b2894c229092ada30999cc10~tplv-pk90l89vgd-crop-center:864:486\\.avif",
            "cookies": 0,
            "fingerprinting": 0,
            "subdomains": [
                "p3-sign"
            ],
            "apis": {},
            "sites": 2,
            "prevalence": 0.0000135,
            "cnames": [],
            "responseHashes": [
                "e757b3e6f82cf6ca11998ff32e10c70f1fe06d3f06f44e949dce99188751d7ba"
            ],
            "type": "Image",
            "firstPartyCookies": {},
            "firstPartyCookiesSent": {},
            "exampleSites": [
                "ixigua.com",
                "www.ixigua.com"
            ]
        },
        {
            "rule": "bdxiguaimg\\.com\\/tos-cn-i-0004\\/f21a3902b01e4181aad71fd17d173eb6~tplv-pk90l89vgd-crop-center:864:486\\.avif",
            "cookies": 0,
            "fingerprinting": 0,
            "subdomains": [
                "p26-sign"
            ],
            "apis": {},
            "sites": 2,
            "prevalence": 0.0000135,
            "cnames": [],
            "responseHashes": [
                "40d1aec3e57c5c8b35f66fb4c11a9739112f101bcfc2bac7410a1ffa342e522f"
            ],
            "type": "Image",
            "firstPartyCookies": {},
            "firstPartyCookiesSent": {},
            "exampleSites": [
                "ixigua.com",
                "www.ixigua.com"
            ]
        },
        {
            "rule": "bdxiguaimg\\.com\\/tos-cn-i-0004\\/50a2a2d2c24b454db95b1b398c003bbb~tplv-pk90l89vgd-crop-center:864:486\\.avif",
            "cookies": 0,
            "fingerprinting": 0,
            "subdomains": [
                "p6-sign"
            ],
            "apis": {},
            "sites": 2,
            "prevalence": 0.0000135,
            "cnames": [],
            "responseHashes": [
                "7f15a5cb4a8ae26aa1375167a7db0114f753e0a5af675e9d2197c75866247c1f"
            ],
            "type": "Image",
            "firstPartyCookies": {},
            "firstPartyCookiesSent": {},
            "exampleSites": [
                "ixigua.com",
                "www.ixigua.com"
            ]
        },
        {
            "rule": "bdxiguaimg\\.com\\/tos-cn-i-0026\\/321336b6e0944d25a28f1d76feb2e025~tplv-pk90l89vgd-crop-center:864:486\\.avif",
            "cookies": 0,
            "fingerprinting": 0,
            "subdomains": [
                "p3-sign"
            ],
            "apis": {},
            "sites": 2,
            "prevalence": 0.0000135,
            "cnames": [],
            "responseHashes": [
                "7fdc2163ea0a7834ec29fd4a4baf22be243e6ba4d30c6bcc93f3785ea61f75bd"
            ],
            "type": "Image",
            "firstPartyCookies": {},
            "firstPartyCookiesSent": {},
            "exampleSites": [
                "ixigua.com",
                "www.ixigua.com"
            ]
        },
        {
            "rule": "bdxiguaimg\\.com\\/tos-cn-i-0004\\/0986e8790d9c44a5bbc42533a0926891~tplv-pk90l89vgd-crop-center:864:486\\.avif",
            "cookies": 0,
            "fingerprinting": 0,
            "subdomains": [
                "p26-sign"
            ],
            "apis": {},
            "sites": 2,
            "prevalence": 0.0000135,
            "cnames": [],
            "responseHashes": [
                "93af0b6f986661331bc43764fca1b745a9dcad17fa461d3361611c0d77dbe3f5"
            ],
            "type": "Image",
            "firstPartyCookies": {},
            "firstPartyCookiesSent": {},
            "exampleSites": [
                "ixigua.com",
                "www.ixigua.com"
            ]
        },
        {
            "rule": "bdxiguaimg\\.com\\/tos-cn-i-0004\\/0b5d6887984f4c7e93022c34b5e15f9d~tplv-pk90l89vgd-crop-center:864:486\\.avif",
            "cookies": 0,
            "fingerprinting": 0,
            "subdomains": [
                "p3-sign"
            ],
            "apis": {},
            "sites": 2,
            "prevalence": 0.0000135,
            "cnames": [],
            "responseHashes": [
                "a492903430fe0111cce4b5de74609107d780b4ce4fb9f323ef9a6a017d9ded2d"
            ],
            "type": "Image",
            "firstPartyCookies": {},
            "firstPartyCookiesSent": {},
            "exampleSites": [
                "ixigua.com",
                "www.ixigua.com"
            ]
        },
        {
            "rule": "bdxiguaimg\\.com\\/tos-cn-i-0004\\/8655d9742f2847aca2a6b084b6671253~tplv-pk90l89vgd-crop-center:864:486\\.avif",
            "cookies": 0,
            "fingerprinting": 0,
            "subdomains": [
                "p26-sign"
            ],
            "apis": {},
            "sites": 2,
            "prevalence": 0.0000135,
            "cnames": [],
            "responseHashes": [
                "e56f488469aabc3ed56b03abfbea061bcfe0d2c844ae20ddaf6a6d6b15d52396"
            ],
            "type": "Image",
            "firstPartyCookies": {},
            "firstPartyCookiesSent": {},
            "exampleSites": [
                "ixigua.com",
                "www.ixigua.com"
            ]
        },
        {
            "rule": "bdxiguaimg\\.com\\/tos-cn-i-0004\\/618b5c89aabe4435be64c611941524b2~tplv-pk90l89vgd-crop-center:864:486\\.avif",
            "cookies": 0,
            "fingerprinting": 0,
            "subdomains": [
                "p6-sign"
            ],
            "apis": {},
            "sites": 2,
            "prevalence": 0.0000135,
            "cnames": [],
            "responseHashes": [
                "a3108c7dd7f07009cc9e104ca68beb9bccda589e92764333acdd0378a891ad0a"
            ],
            "type": "Image",
            "firstPartyCookies": {},
            "firstPartyCookiesSent": {},
            "exampleSites": [
                "ixigua.com",
                "www.ixigua.com"
            ]
        },
        {
            "rule": "bdxiguaimg\\.com\\/tos-cn-i-0004\\/2ad5ae5a52664df0ac73a4fb69a50800~tplv-pk90l89vgd-crop-center:864:486\\.avif",
            "cookies": 0,
            "fingerprinting": 0,
            "subdomains": [
                "p6-sign"
            ],
            "apis": {},
            "sites": 2,
            "prevalence": 0.0000135,
            "cnames": [],
            "responseHashes": [
                "a765d4cd2d443cc41a4a660ed500f7e5c64a2704e0d7cd2e4e756b3fa4d38842"
            ],
            "type": "Image",
            "firstPartyCookies": {},
            "firstPartyCookiesSent": {},
            "exampleSites": [
                "ixigua.com",
                "www.ixigua.com"
            ]
        },
        {
            "rule": "bdxiguaimg\\.com\\/tos-cn-i-0004\\/3175b649a26745a59341a68bb318bba1~tplv-pk90l89vgd-crop-center:864:486\\.avif",
            "cookies": 0,
            "fingerprinting": 0,
            "subdomains": [
                "p3-sign"
            ],
            "apis": {},
            "sites": 2,
            "prevalence": 0.0000135,
            "cnames": [],
            "responseHashes": [
                "26c6f42d2519db144951245b78f5cc3aaae643235ede5db7e26fd389ebf62a83"
            ],
            "type": "Image",
            "firstPartyCookies": {},
            "firstPartyCookiesSent": {},
            "exampleSites": [
                "ixigua.com",
                "www.ixigua.com"
            ]
        },
        {
            "rule": "bdxiguaimg\\.com\\/tos-cn-i-0026\\/4296ab22baf04e208617ae8ffb03065c~tplv-pk90l89vgd-crop-center:864:486\\.avif",
            "cookies": 0,
            "fingerprinting": 0,
            "subdomains": [
                "p6-sign"
            ],
            "apis": {},
            "sites": 2,
            "prevalence": 0.0000135,
            "cnames": [],
            "responseHashes": [
                "b65fd5d5ddf271b710447341dca2c4b94841d40c7f6c57b96fe6cbee699c2a56"
            ],
            "type": "Image",
            "firstPartyCookies": {},
            "firstPartyCookiesSent": {},
            "exampleSites": [
                "ixigua.com",
                "www.ixigua.com"
            ]
        },
        {
            "rule": "bdxiguaimg\\.com\\/tos-cn-i-0004\\/c30bdf8afd704ee6a3bdf6d0ee6cff5f~tplv-pk90l89vgd-crop-center:864:486\\.avif",
            "cookies": 0,
            "fingerprinting": 0,
            "subdomains": [
                "p3-sign"
            ],
            "apis": {},
            "sites": 2,
            "prevalence": 0.0000135,
            "cnames": [],
            "responseHashes": [
                "a0166e147e343dd861c74141f0d54548118a2ec51c5b5525ea4233de9ea9367c"
            ],
            "type": "Image",
            "firstPartyCookies": {},
            "firstPartyCookiesSent": {},
            "exampleSites": [
                "ixigua.com",
                "www.ixigua.com"
            ]
        },
        {
            "rule": "bdxiguaimg\\.com\\/tos-cn-i-0004\\/c7057524b0b04a1b8fbdad622d391691~tplv-pk90l89vgd-crop-center:864:486\\.avif",
            "cookies": 0,
            "fingerprinting": 0,
            "subdomains": [
                "p3-sign"
            ],
            "apis": {},
            "sites": 2,
            "prevalence": 0.0000135,
            "cnames": [],
            "responseHashes": [
                "1cfbe936eaf987bc102783c5c1f339fc3d91080b54f5888e8af26b1b40d09031"
            ],
            "type": "Image",
            "firstPartyCookies": {},
            "firstPartyCookiesSent": {},
            "exampleSites": [
                "ixigua.com",
                "www.ixigua.com"
            ]
        },
        {
            "rule": "bdxiguaimg\\.com\\/tos-cn-i-0004\\/96fc02d040be4b7d8f056cb16119ef4a~tplv-pk90l89vgd-crop-center:864:486\\.avif",
            "cookies": 0,
            "fingerprinting": 0,
            "subdomains": [
                "p3-sign"
            ],
            "apis": {},
            "sites": 2,
            "prevalence": 0.0000135,
            "cnames": [],
            "responseHashes": [
                "bca43ef183f7cd155e001370b6c250e19e6eb29e0da972a19a1504cd395c5e98"
            ],
            "type": "Image",
            "firstPartyCookies": {},
            "firstPartyCookiesSent": {},
            "exampleSites": [
                "ixigua.com",
                "www.ixigua.com"
            ]
        },
        {
            "rule": "bdxiguaimg\\.com\\/tos-cn-i-0004\\/69585e2996b043ed90e77e2a5b38f447~tplv-pk90l89vgd-crop-center:864:486\\.avif",
            "cookies": 0,
            "fingerprinting": 0,
            "subdomains": [
                "p3-sign"
            ],
            "apis": {},
            "sites": 2,
            "prevalence": 0.0000135,
            "cnames": [],
            "responseHashes": [
                "09615a8f252a644744d5079248bb97cc577f61685b111ae53e63a893672bcb25"
            ],
            "type": "Image",
            "firstPartyCookies": {},
            "firstPartyCookiesSent": {},
            "exampleSites": [
                "ixigua.com",
                "www.ixigua.com"
            ]
        },
        {
            "rule": "bdxiguaimg\\.com\\/tos-cn-i-0004\\/e512c89fabb747e59a7c9c7f314d9c71~tplv-pk90l89vgd-crop-center:864:486\\.avif",
            "cookies": 0,
            "fingerprinting": 0,
            "subdomains": [
                "p3-sign"
            ],
            "apis": {},
            "sites": 2,
            "prevalence": 0.0000135,
            "cnames": [],
            "responseHashes": [
                "0087dfe538cb277540f43cc6aad1ea9fae08cf8bbc34ece7ef2e91ad5e39c228"
            ],
            "type": "Image",
            "firstPartyCookies": {},
            "firstPartyCookiesSent": {},
            "exampleSites": [
                "ixigua.com",
                "www.ixigua.com"
            ]
        },
        {
            "rule": "bdxiguaimg\\.com\\/tos-cn-i-0004\\/fbce23ba97b342968d02c48a2d143f95~tplv-pk90l89vgd-crop-center:864:486\\.avif",
            "cookies": 0,
            "fingerprinting": 0,
            "subdomains": [
                "p3-sign"
            ],
            "apis": {},
            "sites": 2,
            "prevalence": 0.0000135,
            "cnames": [],
            "responseHashes": [
                "a7f3b06b1af9647e1d716f55383da2ce6beecebd065ba3606ffee1c14e9142d5"
            ],
            "type": "Image",
            "firstPartyCookies": {},
            "firstPartyCookiesSent": {},
            "exampleSites": [
                "ixigua.com",
                "www.ixigua.com"
            ]
        },
        {
            "rule": "bdxiguaimg\\.com\\/tos-cn-i-0026\\/ffde18b9858a4371bc3d031f8a06df4d~tplv-pk90l89vgd-crop-center:864:486\\.avif",
            "cookies": 0,
            "fingerprinting": 0,
            "subdomains": [
                "p3-sign"
            ],
            "apis": {},
            "sites": 2,
            "prevalence": 0.0000135,
            "cnames": [],
            "responseHashes": [
                "70afd3a401c8f66da72cec19fa136e119f3aa90a609cdce6c5aa60e6410b0a68"
            ],
            "type": "Image",
            "firstPartyCookies": {},
            "firstPartyCookiesSent": {},
            "exampleSites": [
                "ixigua.com",
                "www.ixigua.com"
            ]
        },
        {
            "rule": "bdxiguaimg\\.com\\/tos-cn-i-0004\\/abeef5d7fd774b3abdb0946aeca12051~tplv-pk90l89vgd-crop-center:864:486\\.avif",
            "cookies": 0,
            "fingerprinting": 0,
            "subdomains": [
                "p3-sign"
            ],
            "apis": {},
            "sites": 2,
            "prevalence": 0.0000135,
            "cnames": [],
            "responseHashes": [
                "8e6aeec28474de589272fe8ab5ea5ca8503d54541720b517715a3f5799ac9a8c"
            ],
            "type": "Image",
            "firstPartyCookies": {},
            "firstPartyCookiesSent": {},
            "exampleSites": [
                "ixigua.com",
                "www.ixigua.com"
            ]
        },
        {
            "rule": "bdxiguaimg\\.com\\/tos-cn-i-0004\\/900d93bfaf894561a407053608ccf9d8~tplv-pk90l89vgd-crop-center:864:486\\.avif",
            "cookies": 0,
            "fingerprinting": 0,
            "subdomains": [
                "p26-sign"
            ],
            "apis": {},
            "sites": 2,
            "prevalence": 0.0000135,
            "cnames": [],
            "responseHashes": [
                "6d34cc6cd09071449172718db6e1f644493c53c64e9dd3545822a4c28cd3e078"
            ],
            "type": "Image",
            "firstPartyCookies": {},
            "firstPartyCookiesSent": {},
            "exampleSites": [
                "ixigua.com",
                "www.ixigua.com"
            ]
        },
        {
            "rule": "bdxiguaimg\\.com\\/tos-cn-i-0004\\/3ad861fb39df4312bc8c3797d82e6f62~tplv-pk90l89vgd-crop-center:864:486\\.avif",
            "cookies": 0,
            "fingerprinting": 0,
            "subdomains": [
                "p6-sign"
            ],
            "apis": {},
            "sites": 2,
            "prevalence": 0.0000135,
            "cnames": [],
            "responseHashes": [
                "6ba787ea163526765149226190668555d75b4bbd32a5c0aff67a9b5561625a13"
            ],
            "type": "Image",
            "firstPartyCookies": {},
            "firstPartyCookiesSent": {},
            "exampleSites": [
                "ixigua.com",
                "www.ixigua.com"
            ]
        },
        {
            "rule": "bdxiguaimg\\.com\\/tos-cn-i-0004\\/ece689b421c9428e816098676d5d07d9~tplv-pk90l89vgd-crop-center:864:486\\.avif",
            "cookies": 0,
            "fingerprinting": 0,
            "subdomains": [
                "p6-sign"
            ],
            "apis": {},
            "sites": 2,
            "prevalence": 0.0000135,
            "cnames": [],
            "responseHashes": [
                "e23ae60822837b880966543589214f5f00d2de1c533e3d9263e2d23f94cf8a7c"
            ],
            "type": "Image",
            "firstPartyCookies": {},
            "firstPartyCookiesSent": {},
            "exampleSites": [
                "ixigua.com",
                "www.ixigua.com"
            ]
        },
        {
            "rule": "bdxiguaimg\\.com\\/tos-cn-i-0004\\/045447c8c0644f7a90fd6ac68c07f3ef~tplv-pk90l89vgd-crop-center:864:486\\.avif",
            "cookies": 0,
            "fingerprinting": 0,
            "subdomains": [
                "p26-sign"
            ],
            "apis": {},
            "sites": 2,
            "prevalence": 0.0000135,
            "cnames": [],
            "responseHashes": [
                "0901a534f993eb2f791892ae4cb466c7e96e8a9953de8ec03bce31bc5eb92da1"
            ],
            "type": "Image",
            "firstPartyCookies": {},
            "firstPartyCookiesSent": {},
            "exampleSites": [
                "ixigua.com",
                "www.ixigua.com"
            ]
        },
        {
            "rule": "bdxiguaimg\\.com\\/tos-cn-i-0004\\/43c5fe4523304d42a017df4907c0d010~tplv-pk90l89vgd-crop-center:864:486\\.avif",
            "cookies": 0,
            "fingerprinting": 0,
            "subdomains": [
                "p6-sign"
            ],
            "apis": {},
            "sites": 2,
            "prevalence": 0.0000135,
            "cnames": [],
            "responseHashes": [
                "5681aa3a1bb05306b95a46d5a5a62e96211e743cdbfe0261a1adb33b1ad923ce"
            ],
            "type": "Image",
            "firstPartyCookies": {},
            "firstPartyCookiesSent": {},
            "exampleSites": [
                "ixigua.com",
                "www.ixigua.com"
            ]
        },
        {
            "rule": "bdxiguaimg\\.com\\/tos-cn-i-0004\\/900582b30f5447458648c85a793d61f6~tplv-pk90l89vgd-crop-center:864:486\\.avif",
            "cookies": 0,
            "fingerprinting": 0,
            "subdomains": [
                "p26-sign"
            ],
            "apis": {},
            "sites": 2,
            "prevalence": 0.0000135,
            "cnames": [],
            "responseHashes": [
                "1fb8ae313d43cb3312955110e75b13adce4796a3abd23c44410b98bb0931412c"
            ],
            "type": "Image",
            "firstPartyCookies": {},
            "firstPartyCookiesSent": {},
            "exampleSites": [
                "ixigua.com",
                "www.ixigua.com"
            ]
        }
    ],
    "categories": [],
    "performance": {},
    "cookies": 0,
    "topInitiators": [
        {
            "domain": "bytescm.com",
            "prevalence": 0.39669421487603307
        },
        {
            "domain": "bdxiguastatic.com",
            "prevalence": 0.30578512396694213
        },
        {
            "domain": "first party",
            "prevalence": 0.2975206611570248
        }
    ],
    "types": {
        "Image": 96
    },
    "nameservers": [
        "vip3.alidns.com",
        "vip4.alidns.com"
    ]
}