{
    "domain": "bimbim.com",
    "owner": {},
    "source": [
        "DuckDuckGo-US"
    ],
    "prevalence": 0.0000271,
    "sites": 4,
    "subdomains": [
        "vast"
    ],
    "cnames": [],
    "fingerprinting": 0,
    "resources": [
        {
            "rule": "bimbim\\.com\\/vast\\/v3\\/bb",
            "cookies": 0.0000271,
            "fingerprinting": 0,
            "subdomains": [
                "vast"
            ],
            "apis": {},
            "sites": 4,
            "prevalence": 0.0000271,
            "cnames": [],
            "responseHashes": [
                "cb3afb331115cb3f5fd266c5da2873e57eac9ab597c4e0581bbc2a7cd6477f74",
                "41ab97dd5be867aeb4c0f7427c0daead273ca1e3a1e7cf2cf9296a55dfff4475",
                "b48037c8700da9ead62c431bb946cbd818e836d43785a18004e1539e6effa26d"
            ],
            "type": "Fetch",
            "firstPartyCookies": {},
            "firstPartyCookiesSent": {},
            "exampleSites": [
                "gay.bingo",
                "de.hdsex.org",
                "shemale.taxi",
                "www.analdin.xxx"
            ]
        }
    ],
    "categories": [],
    "performance": {},
    "cookies": 0.0000271,
    "topInitiators": [
        {
            "domain": "qhip.com",
            "prevalence": 0.25
        },
        {
            "domain": "qoqv.com",
            "prevalence": 0.25
        },
        {
            "domain": "h-ay.com",
            "prevalence": 0.25
        },
        {
            "domain": "hitfuck.icu",
            "prevalence": 0.25
        }
    ],
    "types": {
        "Fetch": 4
    },
    "nameservers": [
        "ns2.dditservices.com",
        "ns1.dditservices.com"
    ]
}