{
    "domain": "computerhoy.com",
    "owner": {
        "name": "HOBBY PRESS SA",
        "displayName": "HOBBY PRESS"
    },
    "source": [
        "DuckDuckGo-US"
    ],
    "prevalence": 0.0000136,
    "sites": 2,
    "subdomains": [
        "cdn"
    ],
    "cnames": [],
    "fingerprinting": 0,
    "resources": [
        {
            "rule": "computerhoy\\.com\\/sites\\/navi\\.axelspringer\\.es\\/public\\/media\\/image\\/2021\\/05\\/susto-movil-2337741\\.jpg",
            "cookies": 0,
            "fingerprinting": 0,
            "subdomains": [
                "cdn"
            ],
            "apis": {},
            "sites": 2,
            "prevalence": 0.0000136,
            "cnames": [],
            "responseHashes": [
                "53a11515c999abc39ddbccce3eb12d3f28992a28d170cd816e2d9c2ea97adaf9"
            ],
            "type": "Image",
            "firstPartyCookies": {},
            "firstPartyCookiesSent": {},
            "exampleSites": [
                "gearrice.com",
                "www.gearrice.com"
            ]
        }
    ],
    "categories": [],
    "performance": {},
    "cookies": 0,
    "topInitiators": [
        {
            "domain": "first party",
            "prevalence": 1
        }
    ],
    "types": {
        "Image": 2
    },
    "nameservers": [
        "clint.ns.cloudflare.com",
        "kristin.ns.cloudflare.com"
    ]
}