{
    "domain": "flipsnack.com",
    "owner": {},
    "source": [
        "DuckDuckGo-US"
    ],
    "prevalence": 0.0000339,
    "sites": 5,
    "subdomains": [
        "player",
        "cdn"
    ],
    "cnames": [],
    "fingerprinting": 2,
    "resources": [
        {
            "rule": "flipsnack\\.com\\/",
            "cookies": 0,
            "fingerprinting": 1,
            "subdomains": [
                "player"
            ],
            "apis": {
                "window.innerWidth": 3,
                "window.innerHeight": 3
            },
            "sites": 3,
            "prevalence": 0.0000203,
            "cnames": [],
            "responseHashes": [
                "e93d2872f6ed836c92e3fb5e59aedd77d54fd4a55018937423ebb6c92ce433a6"
            ],
            "type": "Document",
            "firstPartyCookies": {},
            "firstPartyCookiesSent": {},
            "exampleSites": [
                "trinidadexpress.com",
                "www.diariocordoba.com",
                "www.eastvalleytribune.com"
            ]
        },
        {
            "rule": "flipsnack\\.com\\/reader\\.gz\\.js",
            "cookies": 0,
            "fingerprinting": 2,
            "subdomains": [
                "player"
            ],
            "apis": {
                "window.localStorage": 3,
                "Navigator.prototype.userAgent": 3,
                "Navigator.prototype.platform": 3,
                "Document.cookie getter": 3,
                "window.innerWidth": 1,
                "window.innerHeight": 1,
                "Date.prototype.getTime": 1,
                "Screen.prototype.width": 1,
                "Screen.prototype.height": 1
            },
            "sites": 3,
            "prevalence": 0.0000203,
            "cnames": [],
            "responseHashes": [
                "9840e99a8ef2a949a7deceb828d46b69a9e74b36f1363ad198cb928bd2d07310"
            ],
            "type": "Script",
            "firstPartyCookies": {},
            "firstPartyCookiesSent": {},
            "exampleSites": [
                "trinidadexpress.com",
                "www.diariocordoba.com",
                "www.eastvalleytribune.com"
            ]
        },
        {
            "rule": "flipsnack\\.com\\/handleUnsupportedBrowsers\\.gz\\.js",
            "cookies": 0,
            "fingerprinting": 0,
            "subdomains": [
                "player"
            ],
            "apis": {},
            "sites": 3,
            "prevalence": 0.0000203,
            "cnames": [],
            "responseHashes": [
                "9aee5d8ed6a872a72cc241f845f2e920fde4e88c1c9a1afeeb9c850c77f910df"
            ],
            "type": "Script",
            "firstPartyCookies": {},
            "firstPartyCookiesSent": {},
            "exampleSites": [
                "trinidadexpress.com",
                "www.diariocordoba.com",
                "www.eastvalleytribune.com"
            ]
        },
        {
            "rule": "flipsnack\\.com\\/widget\\/v2\\/widget\\.html",
            "cookies": 0,
            "fingerprinting": 1,
            "subdomains": [
                "cdn"
            ],
            "apis": {
                "Navigator.prototype.userAgent": 2,
                "Navigator.prototype.appVersion": 2
            },
            "sites": 2,
            "prevalence": 0.0000136,
            "cnames": [],
            "responseHashes": [
                "9bec368a9e3975c4b1f06495522ec30518b594c6d755adfefcb559dd9acdbb9e"
            ],
            "type": "Document",
            "firstPartyCookies": {},
            "firstPartyCookiesSent": {},
            "exampleSites": [
                "shars.com",
                "www.shars.com"
            ]
        },
        {
            "rule": "flipsnack\\.com\\/widget\\/v2\\/main\\.min\\.gz\\.css",
            "cookies": 0,
            "fingerprinting": 0,
            "subdomains": [
                "cdn"
            ],
            "apis": {},
            "sites": 2,
            "prevalence": 0.0000136,
            "cnames": [],
            "responseHashes": [
                "31cb8a9b9cacbcbe755fe09ea0884729294caa301f5e66cabb81dbfa7e9bceeb"
            ],
            "type": "Stylesheet",
            "firstPartyCookies": {},
            "firstPartyCookiesSent": {},
            "exampleSites": [
                "shars.com",
                "www.shars.com"
            ]
        },
        {
            "rule": "flipsnack\\.com\\/widget\\/v2\\/desktop\\.min\\.gz\\.css",
            "cookies": 0,
            "fingerprinting": 0,
            "subdomains": [
                "cdn"
            ],
            "apis": {},
            "sites": 2,
            "prevalence": 0.0000136,
            "cnames": [],
            "responseHashes": [
                "44daffccb9f560d14a426472f1d7b4e527fb4ccb3f9efec14497cc72fc4106ac"
            ],
            "type": "Stylesheet",
            "firstPartyCookies": {},
            "firstPartyCookiesSent": {},
            "exampleSites": [
                "shars.com",
                "www.shars.com"
            ]
        },
        {
            "rule": "flipsnack\\.com\\/widget\\/v2\\/shelf\\.min\\.gz\\.css",
            "cookies": 0,
            "fingerprinting": 0,
            "subdomains": [
                "cdn"
            ],
            "apis": {},
            "sites": 2,
            "prevalence": 0.0000136,
            "cnames": [],
            "responseHashes": [
                "55054d34058a3c7e34c4265607c9ea5278de1ca79889c5ffd353f71cd9611b7c"
            ],
            "type": "Stylesheet",
            "firstPartyCookies": {},
            "firstPartyCookiesSent": {},
            "exampleSites": [
                "shars.com",
                "www.shars.com"
            ]
        },
        {
            "rule": "flipsnack\\.com\\/widget\\/v2\\/theme\\.min\\.gz\\.css",
            "cookies": 0,
            "fingerprinting": 0,
            "subdomains": [
                "cdn"
            ],
            "apis": {},
            "sites": 2,
            "prevalence": 0.0000136,
            "cnames": [],
            "responseHashes": [
                "94f8c7feb22b501cbb1e979d8ec4debc07e53ca3beaa8946366d735168d1f5fe"
            ],
            "type": "Stylesheet",
            "firstPartyCookies": {},
            "firstPartyCookiesSent": {},
            "exampleSites": [
                "shars.com",
                "www.shars.com"
            ]
        },
        {
            "rule": "flipsnack\\.com\\/widget\\/v2\\/main\\.min\\.gz\\.js",
            "cookies": 0,
            "fingerprinting": 2,
            "subdomains": [
                "cdn"
            ],
            "apis": {
                "Navigator.prototype.userAgent": 2,
                "window.devicePixelRatio": 2,
                "Screen.prototype.width": 2,
                "Screen.prototype.height": 2,
                "Date.prototype.getTime": 2,
                "Navigator.prototype.maxTouchPoints": 2,
                "Navigator.prototype.appVersion": 2,
                "Element.prototype.getClientRects": 2,
                "Event.prototype.timeStamp": 2
            },
            "sites": 2,
            "prevalence": 0.0000136,
            "cnames": [],
            "responseHashes": [
                "09e9088f986626a26b2a94455f654caabe5377536725a5dd4cf4f1aa0b3e366a"
            ],
            "type": "Script",
            "firstPartyCookies": {},
            "firstPartyCookiesSent": {},
            "exampleSites": [
                "shars.com",
                "www.shars.com"
            ]
        },
        {
            "rule": "flipsnack\\.com\\/widget\\/v2\\/desktop\\.min\\.gz\\.js",
            "cookies": 0,
            "fingerprinting": 0,
            "subdomains": [
                "cdn"
            ],
            "apis": {},
            "sites": 2,
            "prevalence": 0.0000136,
            "cnames": [],
            "responseHashes": [
                "4b66d48a9c896c57924e87ed2ac4b0880c2dd117fbfb3ade83be828eb9c3205a"
            ],
            "type": "Script",
            "firstPartyCookies": {},
            "firstPartyCookiesSent": {},
            "exampleSites": [
                "shars.com",
                "www.shars.com"
            ]
        },
        {
            "rule": "flipsnack\\.com\\/widget\\/v2\\/customcontent\\.min\\.gz\\.js",
            "cookies": 0,
            "fingerprinting": 0,
            "subdomains": [
                "cdn"
            ],
            "apis": {},
            "sites": 2,
            "prevalence": 0.0000136,
            "cnames": [],
            "responseHashes": [
                "eaf668cfc264e4418cf9a5b9eabaab4090473612025f5a15d4b20a4f5a04d7b3"
            ],
            "type": "Script",
            "firstPartyCookies": {},
            "firstPartyCookiesSent": {},
            "exampleSites": [
                "shars.com",
                "www.shars.com"
            ]
        },
        {
            "rule": "flipsnack\\.com\\/widget\\/v2\\/shelf\\.min\\.gz\\.js",
            "cookies": 0,
            "fingerprinting": 0,
            "subdomains": [
                "cdn"
            ],
            "apis": {},
            "sites": 2,
            "prevalence": 0.0000136,
            "cnames": [],
            "responseHashes": [
                "35b91e9ea00b25df670f951dd9380c1cc90823e43ba9265b893f8c05de1bb2b9"
            ],
            "type": "Script",
            "firstPartyCookies": {},
            "firstPartyCookiesSent": {},
            "exampleSites": [
                "shars.com",
                "www.shars.com"
            ]
        },
        {
            "rule": "flipsnack\\.com\\/templates\\/premium-layouts\\.gz\\.js",
            "cookies": 0,
            "fingerprinting": 0,
            "subdomains": [
                "cdn"
            ],
            "apis": {},
            "sites": 2,
            "prevalence": 0.0000136,
            "cnames": [],
            "responseHashes": [
                "b2a69ba5ed150cca16aa343592800eff35f4bd743c21f89f0ceba622e88bb590"
            ],
            "type": "XHR",
            "firstPartyCookies": {},
            "firstPartyCookiesSent": {},
            "exampleSites": [
                "shars.com",
                "www.shars.com"
            ]
        },
        {
            "rule": "flipsnack\\.com\\/collections\\/json\\/upa758pd1j",
            "cookies": 0,
            "fingerprinting": 0,
            "subdomains": [
                "cdn"
            ],
            "apis": {},
            "sites": 2,
            "prevalence": 0.0000136,
            "cnames": [],
            "responseHashes": [
                "3624a122113089520e125ba868a1dff4253a663f0c1298917df2f82487272bf4"
            ],
            "type": "XHR",
            "firstPartyCookies": {},
            "firstPartyCookiesSent": {},
            "exampleSites": [
                "shars.com",
                "www.shars.com"
            ]
        },
        {
            "rule": "flipsnack\\.com\\/collections\\/items\\/db1e21c31f3624aa281e2ci138202934\\/json\\/links\\.js",
            "cookies": 0,
            "fingerprinting": 0,
            "subdomains": [
                "cdn"
            ],
            "apis": {},
            "sites": 2,
            "prevalence": 0.0000136,
            "cnames": [],
            "responseHashes": [
                "e3b0c44298fc1c149afbf4c8996fb92427ae41e4649b934ca495991b7852b855"
            ],
            "type": "Script",
            "firstPartyCookies": {},
            "firstPartyCookiesSent": {},
            "exampleSites": [
                "shars.com",
                "www.shars.com"
            ]
        },
        {
            "rule": "flipsnack\\.com\\/collections\\/items\\/db1e21c31f3624aa281e2ci138202934\\/json\\/text\\.js",
            "cookies": 0,
            "fingerprinting": 0,
            "subdomains": [
                "cdn"
            ],
            "apis": {},
            "sites": 2,
            "prevalence": 0.0000136,
            "cnames": [],
            "responseHashes": [
                "24dbc4e886d8e446c26b245bfbb6658ef1cc4aa257709c738be858a3cae632e4"
            ],
            "type": "Script",
            "firstPartyCookies": {},
            "firstPartyCookiesSent": {},
            "exampleSites": [
                "shars.com",
                "www.shars.com"
            ]
        },
        {
            "rule": "flipsnack\\.com\\/collections\\/customize\\/l1579207850872\\.png",
            "cookies": 0,
            "fingerprinting": 0,
            "subdomains": [
                "cdn"
            ],
            "apis": {},
            "sites": 2,
            "prevalence": 0.0000136,
            "cnames": [],
            "responseHashes": [
                "da5e3391cb90655ff63133e6a3bb0cea435c32acc6bebfc1cbe1b5ac4ada3e9a"
            ],
            "type": "Image",
            "firstPartyCookies": {},
            "firstPartyCookiesSent": {},
            "exampleSites": [
                "shars.com",
                "www.shars.com"
            ]
        },
        {
            "rule": "flipsnack\\.com\\/collections\\/items\\/db1e21c31f3624aa281e2ci138202934\\/covers\\/page_1\\/medium",
            "cookies": 0,
            "fingerprinting": 0,
            "subdomains": [
                "cdn"
            ],
            "apis": {},
            "sites": 2,
            "prevalence": 0.0000136,
            "cnames": [],
            "responseHashes": [
                "3c9e680c7d66b2062020559c93c988cf35d39db18fc416e1796735b1c747b974"
            ],
            "type": "Image",
            "firstPartyCookies": {},
            "firstPartyCookiesSent": {},
            "exampleSites": [
                "shars.com",
                "www.shars.com"
            ]
        },
        {
            "rule": "flipsnack\\.com\\/collections\\/items\\/db1e21c31f3624aa281e2ci138202934\\/covers\\/page_2\\/medium",
            "cookies": 0,
            "fingerprinting": 0,
            "subdomains": [
                "cdn"
            ],
            "apis": {},
            "sites": 2,
            "prevalence": 0.0000136,
            "cnames": [],
            "responseHashes": [
                "274cae874e2d60a8f5a7511626e76b90825641fa5400b4695455b2f8da8c4a18"
            ],
            "type": "Image",
            "firstPartyCookies": {},
            "firstPartyCookiesSent": {},
            "exampleSites": [
                "shars.com",
                "www.shars.com"
            ]
        },
        {
            "rule": "flipsnack\\.com\\/collections\\/items\\/db1e21c31f3624aa281e2ci138202934\\/covers\\/page_3\\/medium",
            "cookies": 0,
            "fingerprinting": 0,
            "subdomains": [
                "cdn"
            ],
            "apis": {},
            "sites": 2,
            "prevalence": 0.0000136,
            "cnames": [],
            "responseHashes": [
                "4d34ea81d3c73792f758aec6c59805745b54b09d739c8af9718b58eb9a7d0a25"
            ],
            "type": "Image",
            "firstPartyCookies": {},
            "firstPartyCookiesSent": {},
            "exampleSites": [
                "shars.com",
                "www.shars.com"
            ]
        },
        {
            "rule": "flipsnack\\.com\\/collections\\/items\\/db1e21c31f3624aa281e2ci138202934\\/covers\\/page_4\\/medium",
            "cookies": 0,
            "fingerprinting": 0,
            "subdomains": [
                "cdn"
            ],
            "apis": {},
            "sites": 2,
            "prevalence": 0.0000136,
            "cnames": [],
            "responseHashes": [
                "884f335fca8b89ec76898fba7b3ca18751825dec01427b29ff49da036a4996eb"
            ],
            "type": "Image",
            "firstPartyCookies": {},
            "firstPartyCookiesSent": {},
            "exampleSites": [
                "shars.com",
                "www.shars.com"
            ]
        },
        {
            "rule": "flipsnack\\.com\\/collections\\/items\\/db1e21c31f3624aa281e2ci138202934\\/covers\\/page_5\\/medium",
            "cookies": 0,
            "fingerprinting": 0,
            "subdomains": [
                "cdn"
            ],
            "apis": {},
            "sites": 2,
            "prevalence": 0.0000136,
            "cnames": [],
            "responseHashes": [
                "26c3e0a7631bffa4c643fd27b868ac221a96bc4f0bceb4d49ed2f635de5bf308"
            ],
            "type": "Image",
            "firstPartyCookies": {},
            "firstPartyCookiesSent": {},
            "exampleSites": [
                "shars.com",
                "www.shars.com"
            ]
        },
        {
            "rule": "flipsnack\\.com\\/collections\\/items\\/db1e21c31f3624aa281e2ci138202934\\/covers\\/page_6\\/medium",
            "cookies": 0,
            "fingerprinting": 0,
            "subdomains": [
                "cdn"
            ],
            "apis": {},
            "sites": 2,
            "prevalence": 0.0000136,
            "cnames": [],
            "responseHashes": [
                "85a2c8fea39b70307587dd90414bd2b9b50fe9003b649c94367c8ff9f429c5a1"
            ],
            "type": "Image",
            "firstPartyCookies": {},
            "firstPartyCookiesSent": {},
            "exampleSites": [
                "shars.com",
                "www.shars.com"
            ]
        },
        {
            "rule": "flipsnack\\.com\\/widget\\/assets\\/page_flip\\.mp3",
            "cookies": 0,
            "fingerprinting": 0,
            "subdomains": [
                "cdn"
            ],
            "apis": {},
            "sites": 2,
            "prevalence": 0.0000136,
            "cnames": [],
            "responseHashes": [
                "79fb97dc427a0f2c96bf673b20496bb9a6b75b562d90079c1e5439260071c55f"
            ],
            "type": "Media",
            "firstPartyCookies": {},
            "firstPartyCookiesSent": {},
            "exampleSites": [
                "shars.com",
                "www.shars.com"
            ]
        },
        {
            "rule": "flipsnack\\.com\\/collections\\/items\\/b86a9278c04bdd09d40cb0i138202935\\/json\\/text\\.js",
            "cookies": 0,
            "fingerprinting": 0,
            "subdomains": [
                "cdn"
            ],
            "apis": {},
            "sites": 2,
            "prevalence": 0.0000136,
            "cnames": [],
            "responseHashes": [
                "c3a15c57ff4fa8445a487159b8646ccf4e3501de2868f04f2752c9f137073dc0"
            ],
            "type": "Script",
            "firstPartyCookies": {},
            "firstPartyCookiesSent": {},
            "exampleSites": [
                "shars.com",
                "www.shars.com"
            ]
        }
    ],
    "categories": [],
    "performance": {},
    "cookies": 0,
    "topInitiators": [
        {
            "domain": "first party",
            "prevalence": 1
        }
    ],
    "types": {
        "Document": 5,
        "Script": 20,
        "Stylesheet": 8,
        "XHR": 4,
        "Image": 14,
        "Media": 2
    },
    "nameservers": [
        "ns-1616.awsdns-10.co.uk",
        "ns-249.awsdns-31.com",
        "ns-1438.awsdns-51.org",
        "ns-788.awsdns-34.net"
    ]
}