{
    "domain": "geoiplookup.io",
    "owner": {},
    "source": [
        "DuckDuckGo-US"
    ],
    "prevalence": 0.000196,
    "sites": 29,
    "subdomains": [
        "json"
    ],
    "cnames": [],
    "fingerprinting": 0,
    "resources": [
        {
            "rule": "geoiplookup\\.io\\/",
            "cookies": 0,
            "fingerprinting": 0,
            "subdomains": [
                "json"
            ],
            "apis": {},
            "sites": 13,
            "prevalence": 0.000088,
            "cnames": [],
            "responseHashes": [
                "c36663a4332da7ba434614ef76a89eb6b449d40adb00fdf7fda3ee4eb5237de3",
                "8acdac808b500fc0823aaed44861606dfc74f98262d8a450d7be12cfd1d7b9c0",
                "7d03161d3b5b2643fb89783bb53c86d07af490ccb5c06dc855be8652d84a55c1",
                "e4c8a6618a537779506680e3355973912e05be77f6418d2722f1d6ecae6ecf62",
                "334e702012cf0d8dfdbcfe2a9ff9e70032ca59cad3573f01454a3e1706131f5c"
            ],
            "type": "XHR",
            "firstPartyCookies": {},
            "firstPartyCookiesSent": {},
            "exampleSites": [
                "anoeses.com",
                "drjessesantiano.com",
                "healingbrave.com",
                "jujimufu.com",
                "lovehoneyforum.com",
                "optcorp.com",
                "www.allparts.com",
                "www.groveandgrotto.com",
                "www.houseofdenial.com",
                "www.ima-usa.com",
                "www.modiphius.net",
                "www.ruohonjuuri.fi",
                "www.thearcanelibrary.com"
            ]
        },
        {
            "rule": "geoiplookup\\.io\\/",
            "cookies": 0,
            "fingerprinting": 0,
            "subdomains": [
                "json"
            ],
            "apis": {},
            "sites": 2,
            "prevalence": 0.0000135,
            "cnames": [],
            "responseHashes": [
                "c36663a4332da7ba434614ef76a89eb6b449d40adb00fdf7fda3ee4eb5237de3"
            ],
            "type": "Fetch",
            "firstPartyCookies": {},
            "firstPartyCookiesSent": {},
            "exampleSites": [
                "heho.com.tw",
                "www.sena.com"
            ]
        }
    ],
    "categories": [],
    "performance": {},
    "cookies": 0,
    "topInitiators": [
        {
            "domain": "shopify.com",
            "prevalence": 0.7586206896551724
        },
        {
            "domain": "oxra.com.tw",
            "prevalence": 0.06896551724137931
        },
        {
            "domain": "discourse-cdn.com",
            "prevalence": 0.06896551724137931
        },
        {
            "domain": "first party",
            "prevalence": 0.06896551724137931
        },
        {
            "domain": "wp.com",
            "prevalence": 0.034482758620689655
        }
    ],
    "types": {
        "XHR": 13,
        "Fetch": 2
    },
    "nameservers": [
        "adrian.ns.cloudflare.com",
        "buck.ns.cloudflare.com"
    ]
}