{
    "domain": "iheart.map.fastly.net",
    "owner": {
        "name": "Fastly, Inc.",
        "displayName": "Fastly",
        "privacyPolicy": "https://www.fastly.com/privacy",
        "url": "http://fastly.com"
    },
    "source": [
        "DuckDuckGo-US"
    ],
    "prevalence": 0.000186,
    "sites": 24,
    "subdomains": [
        "prod",
        "dualstack.prod"
    ],
    "cnames": [
        {
            "original": "api.iheart.com",
            "resolved": "prod.iheart.map.fastly.net"
        },
        {
            "original": "global.api.iheart.com",
            "resolved": "prod.iheart.map.fastly.net"
        },
        {
            "original": "us.api.iheart.com",
            "resolved": "dualstack.prod.iheart.map.fastly.net"
        }
    ],
    "fingerprinting": 0,
    "resources": [
        {
            "rule": "iheart\\.map\\.fastly\\.net\\/api\\/v3\\/abtest\\/users\\/groups\\/query",
            "cookies": 0,
            "fingerprinting": 0,
            "subdomains": [
                "prod",
                "dualstack.prod"
            ],
            "apis": {},
            "sites": 13,
            "prevalence": 0.000101,
            "cnames": [
                {
                    "original": "api.iheart.com",
                    "resolved": "prod.iheart.map.fastly.net"
                },
                {
                    "original": "us.api.iheart.com",
                    "resolved": "dualstack.prod.iheart.map.fastly.net"
                }
            ],
            "responseHashes": [],
            "type": "Preflight",
            "firstPartyCookies": {},
            "firstPartyCookiesSent": {},
            "exampleSites": [
                "iheart.com",
                "710wor.iheart.com",
                "foxsportsradio.iheart.com",
                "kfan.iheart.com",
                "kfiam640.iheart.com",
                "knst.iheart.com",
                "koacolorado.iheart.com",
                "ktrh.iheart.com",
                "news.iheart.com",
                "newstalk1130.iheart.com",
                "thebuzz.iheart.com",
                "wrko.iheart.com",
                "www.iheart.com"
            ]
        },
        {
            "rule": "iheart\\.map\\.fastly\\.net\\/api\\/v3\\/abtest\\/users\\/groups\\/query",
            "cookies": 0,
            "fingerprinting": 0,
            "subdomains": [
                "prod",
                "dualstack.prod"
            ],
            "apis": {},
            "sites": 13,
            "prevalence": 0.000101,
            "cnames": [
                {
                    "original": "api.iheart.com",
                    "resolved": "prod.iheart.map.fastly.net"
                },
                {
                    "original": "us.api.iheart.com",
                    "resolved": "dualstack.prod.iheart.map.fastly.net"
                }
            ],
            "responseHashes": [
                "8a1bfb56fc4c766d2939fd8fc816cfbd898a37761fffec6b9b83ab6b1f9e33fb",
                "3f1422098be7654e335f0ff8358519afa83759d65dcbfbfae83b0eeb19236e52",
                "697b368da1fa18262e021a943cb27256dc27d56bf1dfa28b3b3658ae0e5e3e99",
                "e3e0a0e031031dc9db4900d6c5aae08cd9204a9e2e51f2f04d60560e4ecb30e7",
                "f2be921777aa80943d6078a26624d170dd8565d90778a27828e964f9549fb679",
                "6f3a0d4d30fe3e060dacb94e4fe10ba910fa11bca3a9f9287ca67eba894a3236",
                "be2b7e317292459b1c05e1b693a62217030d0388e7feb4abb664efc313714496",
                "3fed210fcbedca15afd6c190581152212253fcab37b1c7a7cb61b0c4eb966c8a",
                "08d114598dab697bbb147b38e124223c3d98d3dbb09c55e632d680fe58f9969c",
                "8289a4f0770d991b165486662cedb94479d78df9f03dab4cd269c9c0014f1e42",
                "f004b9239bda9dc57bec9265cb30d958e12b002e4ee0a443d9649ce149a79ff9"
            ],
            "type": "XHR",
            "firstPartyCookies": {},
            "firstPartyCookiesSent": {},
            "exampleSites": [
                "iheart.com",
                "710wor.iheart.com",
                "foxsportsradio.iheart.com",
                "kfan.iheart.com",
                "kfiam640.iheart.com",
                "knst.iheart.com",
                "koacolorado.iheart.com",
                "ktrh.iheart.com",
                "news.iheart.com",
                "newstalk1130.iheart.com",
                "thebuzz.iheart.com",
                "wrko.iheart.com",
                "www.iheart.com"
            ]
        },
        {
            "rule": "iheart\\.map\\.fastly\\.net\\/api\\/v3\\/locationConfig",
            "cookies": 0,
            "fingerprinting": 0,
            "subdomains": [
                "prod",
                "dualstack.prod"
            ],
            "apis": {},
            "sites": 13,
            "prevalence": 0.000101,
            "cnames": [
                {
                    "original": "global.api.iheart.com",
                    "resolved": "prod.iheart.map.fastly.net"
                },
                {
                    "original": "us.api.iheart.com",
                    "resolved": "dualstack.prod.iheart.map.fastly.net"
                }
            ],
            "responseHashes": [
                "3089febdf611bbae83772c451b053340428f6e3f00c4ba29b099c4f70f472bc1",
                "9ad0f9ecef9cd2bce1200e140b2be44f6a88a3452146f50ae7944559268ac516",
                "083a7128e754319e7570c39ffa5d85010fbf479a3842fbe8543b1e462cd6a3b8"
            ],
            "type": "XHR",
            "firstPartyCookies": {},
            "firstPartyCookiesSent": {},
            "exampleSites": [
                "iheart.com",
                "710wor.iheart.com",
                "foxsportsradio.iheart.com",
                "kfan.iheart.com",
                "kfiam640.iheart.com",
                "knst.iheart.com",
                "koacolorado.iheart.com",
                "ktrh.iheart.com",
                "news.iheart.com",
                "newstalk1130.iheart.com",
                "thebuzz.iheart.com",
                "wrko.iheart.com",
                "www.iheart.com"
            ]
        },
        {
            "rule": "iheart\\.map\\.fastly\\.net\\/api\\/v1\\/account\\/loginOrCreateOauthUser",
            "cookies": 0,
            "fingerprinting": 0,
            "subdomains": [
                "dualstack.prod"
            ],
            "apis": {},
            "sites": 12,
            "prevalence": 0.000093,
            "cnames": [
                {
                    "original": "us.api.iheart.com",
                    "resolved": "dualstack.prod.iheart.map.fastly.net"
                }
            ],
            "responseHashes": [],
            "type": "Preflight",
            "firstPartyCookies": {},
            "firstPartyCookiesSent": {},
            "exampleSites": [
                "iheart.com",
                "710wor.iheart.com",
                "foxsportsradio.iheart.com",
                "kfan.iheart.com",
                "kfiam640.iheart.com",
                "knst.iheart.com",
                "ktrh.iheart.com",
                "news.iheart.com",
                "newstalk1130.iheart.com",
                "thebuzz.iheart.com",
                "wrko.iheart.com",
                "www.iheart.com"
            ]
        },
        {
            "rule": "iheart\\.map\\.fastly\\.net\\/api\\/v1\\/account\\/loginOrCreateOauthUser",
            "cookies": 0,
            "fingerprinting": 0,
            "subdomains": [
                "dualstack.prod"
            ],
            "apis": {},
            "sites": 12,
            "prevalence": 0.000093,
            "cnames": [
                {
                    "original": "us.api.iheart.com",
                    "resolved": "dualstack.prod.iheart.map.fastly.net"
                }
            ],
            "responseHashes": [
                "52a19e995e9a463a25faadd21422f175011578a40f48866ece6d9d076a73251c",
                "959ab8c3c884f734d943c4b43e149b598f5b95194578135511ea6548a5920f51",
                "2746c13993177d8509634e15d65a38b64910c5198cb862607f261cb9ac1261b8",
                "0278691d0cd9f0c96b5c09c04b74d22543f8bc747d21831b5f2708dd8524cd00",
                "0da084dcd92d09d23c85538f8f24d51acf1c6414c00b8c40ca4402987d5089da",
                "8974421cc2126e80fbb2c1e9525d8e8c8988c57464c06ef82ff4eb3dbe960586",
                "659eaf2456865e75d933b668ef9092241a0a6ee3229d2aa903f42392fbe7c809",
                "54a0978bb59b01d8b2ea7fa9ad6456c9f992bb9b2bd7c818c3b1261602afd42a",
                "540e843d3478db3c725c6df1485bf60c24b8ccc9572be66455d6731610f319a1",
                "dc6a84f767afd930b8131fcbfffeba425e474d6da361347b74411356e15836f9",
                "dca5f6ac9efef32ccb9b50aaeb5dbfa2ae9f71c5b66fe3e207b71344a66ca333"
            ],
            "type": "XHR",
            "firstPartyCookies": {},
            "firstPartyCookiesSent": {},
            "exampleSites": [
                "iheart.com",
                "710wor.iheart.com",
                "foxsportsradio.iheart.com",
                "kfan.iheart.com",
                "kfiam640.iheart.com",
                "knst.iheart.com",
                "ktrh.iheart.com",
                "news.iheart.com",
                "newstalk1130.iheart.com",
                "thebuzz.iheart.com",
                "wrko.iheart.com",
                "www.iheart.com"
            ]
        },
        {
            "rule": "iheart\\.map\\.fastly\\.net\\/api\\/v3\\/locationConfig",
            "cookies": 0,
            "fingerprinting": 0,
            "subdomains": [
                "dualstack.prod"
            ],
            "apis": {},
            "sites": 12,
            "prevalence": 0.000093,
            "cnames": [
                {
                    "original": "us.api.iheart.com",
                    "resolved": "dualstack.prod.iheart.map.fastly.net"
                }
            ],
            "responseHashes": [],
            "type": "Preflight",
            "firstPartyCookies": {},
            "firstPartyCookiesSent": {},
            "exampleSites": [
                "iheart.com",
                "710wor.iheart.com",
                "foxsportsradio.iheart.com",
                "kfan.iheart.com",
                "kfiam640.iheart.com",
                "knst.iheart.com",
                "ktrh.iheart.com",
                "news.iheart.com",
                "newstalk1130.iheart.com",
                "thebuzz.iheart.com",
                "wrko.iheart.com",
                "www.iheart.com"
            ]
        },
        {
            "rule": "iheart\\.map\\.fastly\\.net\\/api\\/v3\\/live-meta\\/stream\\/5874\\/currentTrackMeta",
            "cookies": 0,
            "fingerprinting": 0,
            "subdomains": [
                "dualstack.prod"
            ],
            "apis": {},
            "sites": 2,
            "prevalence": 0.0000155,
            "cnames": [
                {
                    "original": "us.api.iheart.com",
                    "resolved": "dualstack.prod.iheart.map.fastly.net"
                }
            ],
            "responseHashes": [
                "e3b0c44298fc1c149afbf4c8996fb92427ae41e4649b934ca495991b7852b855"
            ],
            "type": "XHR",
            "firstPartyCookies": {},
            "firstPartyCookiesSent": {},
            "exampleSites": [
                "iheart.com",
                "710wor.iheart.com"
            ]
        },
        {
            "rule": "iheart\\.map\\.fastly\\.net\\/api\\/v3\\/live-meta\\/stream\\/5874\\/currentTrackMeta",
            "cookies": 0,
            "fingerprinting": 0,
            "subdomains": [
                "dualstack.prod"
            ],
            "apis": {},
            "sites": 2,
            "prevalence": 0.0000155,
            "cnames": [
                {
                    "original": "us.api.iheart.com",
                    "resolved": "dualstack.prod.iheart.map.fastly.net"
                }
            ],
            "responseHashes": [],
            "type": "Preflight",
            "firstPartyCookies": {},
            "firstPartyCookiesSent": {},
            "exampleSites": [
                "iheart.com",
                "710wor.iheart.com"
            ]
        },
        {
            "rule": "iheart\\.map\\.fastly\\.net\\/api\\/v3\\/live-meta\\/stream\\/1209\\/currentTrackMeta",
            "cookies": 0,
            "fingerprinting": 0,
            "subdomains": [
                "dualstack.prod"
            ],
            "apis": {},
            "sites": 2,
            "prevalence": 0.0000155,
            "cnames": [
                {
                    "original": "us.api.iheart.com",
                    "resolved": "dualstack.prod.iheart.map.fastly.net"
                }
            ],
            "responseHashes": [
                "e3b0c44298fc1c149afbf4c8996fb92427ae41e4649b934ca495991b7852b855"
            ],
            "type": "XHR",
            "firstPartyCookies": {},
            "firstPartyCookiesSent": {},
            "exampleSites": [
                "iheart.com",
                "kfan.iheart.com"
            ]
        },
        {
            "rule": "iheart\\.map\\.fastly\\.net\\/api\\/v3\\/live-meta\\/stream\\/1209\\/currentTrackMeta",
            "cookies": 0,
            "fingerprinting": 0,
            "subdomains": [
                "dualstack.prod"
            ],
            "apis": {},
            "sites": 2,
            "prevalence": 0.0000155,
            "cnames": [
                {
                    "original": "us.api.iheart.com",
                    "resolved": "dualstack.prod.iheart.map.fastly.net"
                }
            ],
            "responseHashes": [],
            "type": "Preflight",
            "firstPartyCookies": {},
            "firstPartyCookiesSent": {},
            "exampleSites": [
                "iheart.com",
                "kfan.iheart.com"
            ]
        },
        {
            "rule": "iheart\\.map\\.fastly\\.net\\/api\\/v3\\/live-meta\\/stream\\/177\\/currentTrackMeta",
            "cookies": 0,
            "fingerprinting": 0,
            "subdomains": [
                "dualstack.prod"
            ],
            "apis": {},
            "sites": 2,
            "prevalence": 0.0000155,
            "cnames": [
                {
                    "original": "us.api.iheart.com",
                    "resolved": "dualstack.prod.iheart.map.fastly.net"
                }
            ],
            "responseHashes": [
                "e3b0c44298fc1c149afbf4c8996fb92427ae41e4649b934ca495991b7852b855"
            ],
            "type": "XHR",
            "firstPartyCookies": {},
            "firstPartyCookiesSent": {},
            "exampleSites": [
                "iheart.com",
                "kfiam640.iheart.com"
            ]
        },
        {
            "rule": "iheart\\.map\\.fastly\\.net\\/api\\/v3\\/live-meta\\/stream\\/177\\/currentTrackMeta",
            "cookies": 0,
            "fingerprinting": 0,
            "subdomains": [
                "dualstack.prod"
            ],
            "apis": {},
            "sites": 2,
            "prevalence": 0.0000155,
            "cnames": [
                {
                    "original": "us.api.iheart.com",
                    "resolved": "dualstack.prod.iheart.map.fastly.net"
                }
            ],
            "responseHashes": [],
            "type": "Preflight",
            "firstPartyCookies": {},
            "firstPartyCookiesSent": {},
            "exampleSites": [
                "iheart.com",
                "kfiam640.iheart.com"
            ]
        },
        {
            "rule": "iheart\\.map\\.fastly\\.net\\/api\\/v3\\/live-meta\\/stream\\/3282\\/currentTrackMeta",
            "cookies": 0,
            "fingerprinting": 0,
            "subdomains": [
                "dualstack.prod"
            ],
            "apis": {},
            "sites": 2,
            "prevalence": 0.0000155,
            "cnames": [
                {
                    "original": "us.api.iheart.com",
                    "resolved": "dualstack.prod.iheart.map.fastly.net"
                }
            ],
            "responseHashes": [
                "e3b0c44298fc1c149afbf4c8996fb92427ae41e4649b934ca495991b7852b855"
            ],
            "type": "XHR",
            "firstPartyCookies": {},
            "firstPartyCookiesSent": {},
            "exampleSites": [
                "iheart.com",
                "knst.iheart.com"
            ]
        },
        {
            "rule": "iheart\\.map\\.fastly\\.net\\/api\\/v3\\/live-meta\\/stream\\/3282\\/currentTrackMeta",
            "cookies": 0,
            "fingerprinting": 0,
            "subdomains": [
                "dualstack.prod"
            ],
            "apis": {},
            "sites": 2,
            "prevalence": 0.0000155,
            "cnames": [
                {
                    "original": "us.api.iheart.com",
                    "resolved": "dualstack.prod.iheart.map.fastly.net"
                }
            ],
            "responseHashes": [],
            "type": "Preflight",
            "firstPartyCookies": {},
            "firstPartyCookiesSent": {},
            "exampleSites": [
                "iheart.com",
                "knst.iheart.com"
            ]
        },
        {
            "rule": "iheart\\.map\\.fastly\\.net\\/api\\/v3\\/live-meta\\/stream\\/2285\\/currentTrackMeta",
            "cookies": 0,
            "fingerprinting": 0,
            "subdomains": [
                "dualstack.prod"
            ],
            "apis": {},
            "sites": 2,
            "prevalence": 0.0000155,
            "cnames": [
                {
                    "original": "us.api.iheart.com",
                    "resolved": "dualstack.prod.iheart.map.fastly.net"
                }
            ],
            "responseHashes": [
                "e3b0c44298fc1c149afbf4c8996fb92427ae41e4649b934ca495991b7852b855"
            ],
            "type": "XHR",
            "firstPartyCookies": {},
            "firstPartyCookiesSent": {},
            "exampleSites": [
                "iheart.com",
                "ktrh.iheart.com"
            ]
        },
        {
            "rule": "iheart\\.map\\.fastly\\.net\\/api\\/v3\\/live-meta\\/stream\\/2285\\/currentTrackMeta",
            "cookies": 0,
            "fingerprinting": 0,
            "subdomains": [
                "dualstack.prod"
            ],
            "apis": {},
            "sites": 2,
            "prevalence": 0.0000155,
            "cnames": [
                {
                    "original": "us.api.iheart.com",
                    "resolved": "dualstack.prod.iheart.map.fastly.net"
                }
            ],
            "responseHashes": [],
            "type": "Preflight",
            "firstPartyCookies": {},
            "firstPartyCookiesSent": {},
            "exampleSites": [
                "iheart.com",
                "ktrh.iheart.com"
            ]
        },
        {
            "rule": "iheart\\.map\\.fastly\\.net\\/api\\/v2\\/content\\/markets",
            "cookies": 0,
            "fingerprinting": 0,
            "subdomains": [
                "dualstack.prod"
            ],
            "apis": {},
            "sites": 2,
            "prevalence": 0.0000155,
            "cnames": [
                {
                    "original": "us.api.iheart.com",
                    "resolved": "dualstack.prod.iheart.map.fastly.net"
                }
            ],
            "responseHashes": [],
            "type": "Preflight",
            "firstPartyCookies": {},
            "firstPartyCookiesSent": {},
            "exampleSites": [
                "iheart.com",
                "www.iheart.com"
            ]
        },
        {
            "rule": "iheart\\.map\\.fastly\\.net\\/api\\/v2\\/content\\/markets",
            "cookies": 0,
            "fingerprinting": 0,
            "subdomains": [
                "dualstack.prod"
            ],
            "apis": {},
            "sites": 2,
            "prevalence": 0.0000155,
            "cnames": [
                {
                    "original": "us.api.iheart.com",
                    "resolved": "dualstack.prod.iheart.map.fastly.net"
                }
            ],
            "responseHashes": [
                "8cac38baa93995659bf15d33ce103a9dee5b4420b844f5977e3b08f16026b220"
            ],
            "type": "XHR",
            "firstPartyCookies": {},
            "firstPartyCookiesSent": {},
            "exampleSites": [
                "iheart.com",
                "www.iheart.com"
            ]
        },
        {
            "rule": "iheart\\.map\\.fastly\\.net\\/api\\/v3\\/catalog\\/genres",
            "cookies": 0,
            "fingerprinting": 0,
            "subdomains": [
                "dualstack.prod"
            ],
            "apis": {},
            "sites": 2,
            "prevalence": 0.0000155,
            "cnames": [
                {
                    "original": "us.api.iheart.com",
                    "resolved": "dualstack.prod.iheart.map.fastly.net"
                }
            ],
            "responseHashes": [],
            "type": "Preflight",
            "firstPartyCookies": {},
            "firstPartyCookiesSent": {},
            "exampleSites": [
                "iheart.com",
                "www.iheart.com"
            ]
        },
        {
            "rule": "iheart\\.map\\.fastly\\.net\\/api\\/v3\\/catalog\\/genres",
            "cookies": 0,
            "fingerprinting": 0,
            "subdomains": [
                "dualstack.prod"
            ],
            "apis": {},
            "sites": 2,
            "prevalence": 0.0000155,
            "cnames": [
                {
                    "original": "us.api.iheart.com",
                    "resolved": "dualstack.prod.iheart.map.fastly.net"
                }
            ],
            "responseHashes": [
                "9280486180b31660c20b91bb5d85652d6055465ed46430d2fab5a2d5b902449f"
            ],
            "type": "XHR",
            "firstPartyCookies": {},
            "firstPartyCookiesSent": {},
            "exampleSites": [
                "iheart.com",
                "www.iheart.com"
            ]
        },
        {
            "rule": "iheart\\.map\\.fastly\\.net\\/api\\/v2\\/content\\/liveStations\\/6554,4418,1469,4429,5525,4858,5296,4422,6046,1473,7785,6652,4443,5310,4802",
            "cookies": 0,
            "fingerprinting": 0,
            "subdomains": [
                "dualstack.prod"
            ],
            "apis": {},
            "sites": 2,
            "prevalence": 0.0000155,
            "cnames": [
                {
                    "original": "us.api.iheart.com",
                    "resolved": "dualstack.prod.iheart.map.fastly.net"
                }
            ],
            "responseHashes": [
                "7d8c9e228e325c84b3620dfd6de1a15c0a87af11c3511a6a64d73b8c7bdba518"
            ],
            "type": "XHR",
            "firstPartyCookies": {},
            "firstPartyCookiesSent": {},
            "exampleSites": [
                "iheart.com",
                "www.iheart.com"
            ]
        },
        {
            "rule": "iheart\\.map\\.fastly\\.net\\/api\\/v2\\/content\\/liveStations\\/6554,4418,1469,4429,5525,4858,5296,4422,6046,1473,7785,6652,4443,5310,4802",
            "cookies": 0,
            "fingerprinting": 0,
            "subdomains": [
                "dualstack.prod"
            ],
            "apis": {},
            "sites": 2,
            "prevalence": 0.0000155,
            "cnames": [
                {
                    "original": "us.api.iheart.com",
                    "resolved": "dualstack.prod.iheart.map.fastly.net"
                }
            ],
            "responseHashes": [],
            "type": "Preflight",
            "firstPartyCookies": {},
            "firstPartyCookiesSent": {},
            "exampleSites": [
                "iheart.com",
                "www.iheart.com"
            ]
        },
        {
            "rule": "iheart\\.map\\.fastly\\.net\\/api\\/v3\\/oauth\\/triton\\/token",
            "cookies": 0,
            "fingerprinting": 0,
            "subdomains": [
                "dualstack.prod"
            ],
            "apis": {},
            "sites": 2,
            "prevalence": 0.0000155,
            "cnames": [
                {
                    "original": "us.api.iheart.com",
                    "resolved": "dualstack.prod.iheart.map.fastly.net"
                }
            ],
            "responseHashes": [
                "8f544b1438bd9e87018e3ac7d91873e15929360e74e882f3325ec21bf8b09aee"
            ],
            "type": "XHR",
            "firstPartyCookies": {},
            "firstPartyCookiesSent": {},
            "exampleSites": [
                "iheart.com",
                "www.iheart.com"
            ]
        },
        {
            "rule": "iheart\\.map\\.fastly\\.net\\/api\\/v3\\/oauth\\/triton\\/token",
            "cookies": 0,
            "fingerprinting": 0,
            "subdomains": [
                "dualstack.prod"
            ],
            "apis": {},
            "sites": 2,
            "prevalence": 0.0000155,
            "cnames": [
                {
                    "original": "us.api.iheart.com",
                    "resolved": "dualstack.prod.iheart.map.fastly.net"
                }
            ],
            "responseHashes": [],
            "type": "Preflight",
            "firstPartyCookies": {},
            "firstPartyCookiesSent": {},
            "exampleSites": [
                "iheart.com",
                "www.iheart.com"
            ]
        },
        {
            "rule": "iheart\\.map\\.fastly\\.net\\/api\\/v2\\/content\\/liveStations\\/6554",
            "cookies": 0,
            "fingerprinting": 0,
            "subdomains": [
                "dualstack.prod"
            ],
            "apis": {},
            "sites": 2,
            "prevalence": 0.0000155,
            "cnames": [
                {
                    "original": "us.api.iheart.com",
                    "resolved": "dualstack.prod.iheart.map.fastly.net"
                }
            ],
            "responseHashes": [],
            "type": "Preflight",
            "firstPartyCookies": {},
            "firstPartyCookiesSent": {},
            "exampleSites": [
                "iheart.com",
                "www.iheart.com"
            ]
        },
        {
            "rule": "iheart\\.map\\.fastly\\.net\\/api\\/v2\\/content\\/liveStations\\/6554",
            "cookies": 0,
            "fingerprinting": 0,
            "subdomains": [
                "dualstack.prod"
            ],
            "apis": {},
            "sites": 2,
            "prevalence": 0.0000155,
            "cnames": [
                {
                    "original": "us.api.iheart.com",
                    "resolved": "dualstack.prod.iheart.map.fastly.net"
                }
            ],
            "responseHashes": [
                "efcdfd2e821a7a6462d3abdf5863cf57f8110d17af815b0ce80b3ec4d17ae9ff"
            ],
            "type": "XHR",
            "firstPartyCookies": {},
            "firstPartyCookiesSent": {},
            "exampleSites": [
                "iheart.com",
                "www.iheart.com"
            ]
        },
        {
            "rule": "iheart\\.map\\.fastly\\.net\\/api\\/v3\\/live-meta\\/stream\\/6554\\/currentTrackMeta",
            "cookies": 0,
            "fingerprinting": 0,
            "subdomains": [
                "dualstack.prod"
            ],
            "apis": {},
            "sites": 3,
            "prevalence": 0.0000233,
            "cnames": [
                {
                    "original": "us.api.iheart.com",
                    "resolved": "dualstack.prod.iheart.map.fastly.net"
                }
            ],
            "responseHashes": [
                "8f661ecb07a846be6bbd78679bc34d56b151dee9dbba2f37566c4d6199e8b936",
                "34448161f99b5c231621f6b0159977db4a68e815532399fc57156fa02b4554c3"
            ],
            "type": "XHR",
            "firstPartyCookies": {},
            "firstPartyCookiesSent": {},
            "exampleSites": [
                "iheart.com",
                "news.iheart.com",
                "www.iheart.com"
            ]
        },
        {
            "rule": "iheart\\.map\\.fastly\\.net\\/api\\/v3\\/live-meta\\/stream\\/6554\\/currentTrackMeta",
            "cookies": 0,
            "fingerprinting": 0,
            "subdomains": [
                "dualstack.prod"
            ],
            "apis": {},
            "sites": 2,
            "prevalence": 0.0000155,
            "cnames": [
                {
                    "original": "us.api.iheart.com",
                    "resolved": "dualstack.prod.iheart.map.fastly.net"
                }
            ],
            "responseHashes": [],
            "type": "Preflight",
            "firstPartyCookies": {},
            "firstPartyCookiesSent": {},
            "exampleSites": [
                "iheart.com",
                "www.iheart.com"
            ]
        },
        {
            "rule": "iheart\\.map\\.fastly\\.net\\/api\\/v1\\/catalog\\/getTrackByTrackId",
            "cookies": 0,
            "fingerprinting": 0,
            "subdomains": [
                "dualstack.prod"
            ],
            "apis": {},
            "sites": 2,
            "prevalence": 0.0000155,
            "cnames": [
                {
                    "original": "us.api.iheart.com",
                    "resolved": "dualstack.prod.iheart.map.fastly.net"
                }
            ],
            "responseHashes": [],
            "type": "Preflight",
            "firstPartyCookies": {},
            "firstPartyCookiesSent": {},
            "exampleSites": [
                "iheart.com",
                "www.iheart.com"
            ]
        },
        {
            "rule": "iheart\\.map\\.fastly\\.net\\/api\\/v1\\/catalog\\/getTrackByTrackId",
            "cookies": 0,
            "fingerprinting": 0,
            "subdomains": [
                "dualstack.prod"
            ],
            "apis": {},
            "sites": 2,
            "prevalence": 0.0000155,
            "cnames": [
                {
                    "original": "us.api.iheart.com",
                    "resolved": "dualstack.prod.iheart.map.fastly.net"
                }
            ],
            "responseHashes": [
                "71b5c0afe8dc2e677a1920941266e570a867a40dc1098083eb3aa5189610f449"
            ],
            "type": "XHR",
            "firstPartyCookies": {},
            "firstPartyCookiesSent": {},
            "exampleSites": [
                "iheart.com",
                "www.iheart.com"
            ]
        },
        {
            "rule": "iheart\\.map\\.fastly\\.net\\/api\\/v3\\/live-meta\\/stream\\/4245\\/currentTrackMeta",
            "cookies": 0,
            "fingerprinting": 0,
            "subdomains": [
                "dualstack.prod"
            ],
            "apis": {},
            "sites": 2,
            "prevalence": 0.0000155,
            "cnames": [
                {
                    "original": "us.api.iheart.com",
                    "resolved": "dualstack.prod.iheart.map.fastly.net"
                }
            ],
            "responseHashes": [
                "e3b0c44298fc1c149afbf4c8996fb92427ae41e4649b934ca495991b7852b855"
            ],
            "type": "XHR",
            "firstPartyCookies": {},
            "firstPartyCookiesSent": {},
            "exampleSites": [
                "iheart.com",
                "newstalk1130.iheart.com"
            ]
        },
        {
            "rule": "iheart\\.map\\.fastly\\.net\\/api\\/v3\\/live-meta\\/stream\\/4245\\/currentTrackMeta",
            "cookies": 0,
            "fingerprinting": 0,
            "subdomains": [
                "dualstack.prod"
            ],
            "apis": {},
            "sites": 2,
            "prevalence": 0.0000155,
            "cnames": [
                {
                    "original": "us.api.iheart.com",
                    "resolved": "dualstack.prod.iheart.map.fastly.net"
                }
            ],
            "responseHashes": [],
            "type": "Preflight",
            "firstPartyCookies": {},
            "firstPartyCookiesSent": {},
            "exampleSites": [
                "iheart.com",
                "newstalk1130.iheart.com"
            ]
        },
        {
            "rule": "iheart\\.map\\.fastly\\.net\\/api\\/v3\\/live-meta\\/stream\\/2281\\/currentTrackMeta",
            "cookies": 0,
            "fingerprinting": 0,
            "subdomains": [
                "dualstack.prod"
            ],
            "apis": {},
            "sites": 2,
            "prevalence": 0.0000155,
            "cnames": [
                {
                    "original": "us.api.iheart.com",
                    "resolved": "dualstack.prod.iheart.map.fastly.net"
                }
            ],
            "responseHashes": [
                "4d636da95507f5af5810de8a329adfc3da63b0be9d8a2af4831fb53fad5267a8"
            ],
            "type": "XHR",
            "firstPartyCookies": {},
            "firstPartyCookiesSent": {},
            "exampleSites": [
                "iheart.com",
                "thebuzz.iheart.com"
            ]
        },
        {
            "rule": "iheart\\.map\\.fastly\\.net\\/api\\/v3\\/live-meta\\/stream\\/2281\\/currentTrackMeta",
            "cookies": 0,
            "fingerprinting": 0,
            "subdomains": [
                "dualstack.prod"
            ],
            "apis": {},
            "sites": 2,
            "prevalence": 0.0000155,
            "cnames": [
                {
                    "original": "us.api.iheart.com",
                    "resolved": "dualstack.prod.iheart.map.fastly.net"
                }
            ],
            "responseHashes": [],
            "type": "Preflight",
            "firstPartyCookies": {},
            "firstPartyCookiesSent": {},
            "exampleSites": [
                "iheart.com",
                "thebuzz.iheart.com"
            ]
        },
        {
            "rule": "iheart\\.map\\.fastly\\.net\\/api\\/v3\\/live-meta\\/stream\\/7750\\/currentTrackMeta",
            "cookies": 0,
            "fingerprinting": 0,
            "subdomains": [
                "dualstack.prod"
            ],
            "apis": {},
            "sites": 2,
            "prevalence": 0.0000155,
            "cnames": [
                {
                    "original": "us.api.iheart.com",
                    "resolved": "dualstack.prod.iheart.map.fastly.net"
                }
            ],
            "responseHashes": [
                "e3b0c44298fc1c149afbf4c8996fb92427ae41e4649b934ca495991b7852b855"
            ],
            "type": "XHR",
            "firstPartyCookies": {},
            "firstPartyCookiesSent": {},
            "exampleSites": [
                "iheart.com",
                "wrko.iheart.com"
            ]
        },
        {
            "rule": "iheart\\.map\\.fastly\\.net\\/api\\/v3\\/live-meta\\/stream\\/7750\\/currentTrackMeta",
            "cookies": 0,
            "fingerprinting": 0,
            "subdomains": [
                "dualstack.prod"
            ],
            "apis": {},
            "sites": 2,
            "prevalence": 0.0000155,
            "cnames": [
                {
                    "original": "us.api.iheart.com",
                    "resolved": "dualstack.prod.iheart.map.fastly.net"
                }
            ],
            "responseHashes": [],
            "type": "Preflight",
            "firstPartyCookies": {},
            "firstPartyCookiesSent": {},
            "exampleSites": [
                "iheart.com",
                "wrko.iheart.com"
            ]
        },
        {
            "rule": "iheart\\.map\\.fastly\\.net\\/api\\/v3\\/collection\\/user\\/312064750\\/collection\\/YBPn6HA4b5dvUzMW1wuJkr",
            "cookies": 0,
            "fingerprinting": 0,
            "subdomains": [
                "dualstack.prod"
            ],
            "apis": {},
            "sites": 2,
            "prevalence": 0.0000155,
            "cnames": [
                {
                    "original": "us.api.iheart.com",
                    "resolved": "dualstack.prod.iheart.map.fastly.net"
                }
            ],
            "responseHashes": [
                "b55c53033a6b8083bead64c85d320fbe187007a68ff550b4d42fa6102475e129"
            ],
            "type": "XHR",
            "firstPartyCookies": {},
            "firstPartyCookiesSent": {},
            "exampleSites": [
                "iheart.com",
                "www.iheart.com"
            ]
        },
        {
            "rule": "iheart\\.map\\.fastly\\.net\\/api\\/v2\\/content\\/liveStations",
            "cookies": 0,
            "fingerprinting": 0,
            "subdomains": [
                "dualstack.prod"
            ],
            "apis": {},
            "sites": 2,
            "prevalence": 0.0000155,
            "cnames": [
                {
                    "original": "us.api.iheart.com",
                    "resolved": "dualstack.prod.iheart.map.fastly.net"
                }
            ],
            "responseHashes": [
                "90ec88bec1fe51d8d56bf48a5eadf235b88bef0e0748d291e86d846c8f103144"
            ],
            "type": "XHR",
            "firstPartyCookies": {},
            "firstPartyCookiesSent": {},
            "exampleSites": [
                "iheart.com",
                "www.iheart.com"
            ]
        },
        {
            "rule": "iheart\\.map\\.fastly\\.net\\/api\\/v2\\/content\\/liveStations",
            "cookies": 0,
            "fingerprinting": 0,
            "subdomains": [
                "dualstack.prod"
            ],
            "apis": {},
            "sites": 2,
            "prevalence": 0.0000155,
            "cnames": [
                {
                    "original": "us.api.iheart.com",
                    "resolved": "dualstack.prod.iheart.map.fastly.net"
                }
            ],
            "responseHashes": [],
            "type": "Preflight",
            "firstPartyCookies": {},
            "firstPartyCookiesSent": {},
            "exampleSites": [
                "iheart.com",
                "www.iheart.com"
            ]
        }
    ],
    "categories": [
        "Ad Motivated Tracking",
        "Advertising",
        "Analytics",
        "Third-Party Analytics Marketing",
        "Action Pixels",
        "CDN",
        "Embedded Content",
        "Session Replay"
    ],
    "performance": {},
    "cookies": 0,
    "topInitiators": [
        {
            "domain": "gbqofs.com",
            "prevalence": 0.875
        },
        {
            "domain": "aptivada.com",
            "prevalence": 0.125
        }
    ],
    "types": {
        "Preflight": 69,
        "XHR": 73
    },
    "nameservers": []
}