{
    "domain": "newscentermaine.com.edgekey.net",
    "owner": {
        "name": "Akamai Technologies",
        "displayName": "Akamai",
        "privacyPolicy": "https://www.akamai.com/us/en/privacy-policies/",
        "url": "http://akamai.com"
    },
    "source": [
        "DuckDuckGo-US"
    ],
    "prevalence": 0.0000155,
    "sites": 2,
    "subdomains": [
        "media"
    ],
    "cnames": [
        {
            "original": "media.newscentermaine.com",
            "resolved": "media.newscentermaine.com.edgekey.net"
        }
    ],
    "fingerprinting": 0,
    "resources": [
        {
            "rule": "newscentermaine\\.com\\.edgekey\\.net\\/assets\\/NCM\\/images\\/a2cb9d6a-d69d-41c4-a3a5-eb3abf422745\\/a2cb9d6a-d69d-41c4-a3a5-eb3abf422745_16x9\\.jpg",
            "cookies": 0,
            "fingerprinting": 0,
            "subdomains": [
                "media"
            ],
            "apis": {},
            "sites": 2,
            "prevalence": 0.0000155,
            "cnames": [
                {
                    "original": "media.newscentermaine.com",
                    "resolved": "media.newscentermaine.com.edgekey.net"
                }
            ],
            "responseHashes": [
                "e65f127c13c8b48a2ac5b972fe6f8479804e64b2a5eb21e10cf90a4d08d3f6e1"
            ],
            "type": "Image",
            "firstPartyCookies": {},
            "firstPartyCookiesSent": {},
            "exampleSites": [
                "newscentermaine.com",
                "www.newscentermaine.com"
            ]
        },
        {
            "rule": "newscentermaine\\.com\\.edgekey\\.net\\/assets\\/NCM\\/images\\/ff22e051-762d-4e55-95a0-73436f226669\\/ff22e051-762d-4e55-95a0-73436f226669_16x9\\.jpg",
            "cookies": 0,
            "fingerprinting": 0,
            "subdomains": [
                "media"
            ],
            "apis": {},
            "sites": 2,
            "prevalence": 0.0000155,
            "cnames": [
                {
                    "original": "media.newscentermaine.com",
                    "resolved": "media.newscentermaine.com.edgekey.net"
                }
            ],
            "responseHashes": [
                "530d2643317249ebb026fb922f76c7c2dc77c736ff46ab83e5b8e69651a726a8"
            ],
            "type": "Image",
            "firstPartyCookies": {},
            "firstPartyCookiesSent": {},
            "exampleSites": [
                "newscentermaine.com",
                "www.newscentermaine.com"
            ]
        },
        {
            "rule": "newscentermaine\\.com\\.edgekey\\.net\\/assets\\/NCM\\/images\\/1793e891-daff-40f1-80ef-f986d52b7aec\\/1793e891-daff-40f1-80ef-f986d52b7aec_16x9\\.jpg",
            "cookies": 0,
            "fingerprinting": 0,
            "subdomains": [
                "media"
            ],
            "apis": {},
            "sites": 2,
            "prevalence": 0.0000155,
            "cnames": [
                {
                    "original": "media.newscentermaine.com",
                    "resolved": "media.newscentermaine.com.edgekey.net"
                }
            ],
            "responseHashes": [
                "d11b43b2b27c6e9e207e396cf8e9f67fcc2121fbcfe9bb36f8893ee4a5731b3d"
            ],
            "type": "Image",
            "firstPartyCookies": {},
            "firstPartyCookiesSent": {},
            "exampleSites": [
                "newscentermaine.com",
                "www.newscentermaine.com"
            ]
        },
        {
            "rule": "newscentermaine\\.com\\.edgekey\\.net\\/assets\\/NCM\\/images\\/f6796286-552b-4492-befd-ad5f9a109391\\/f6796286-552b-4492-befd-ad5f9a109391_16x9\\.jpg",
            "cookies": 0,
            "fingerprinting": 0,
            "subdomains": [
                "media"
            ],
            "apis": {},
            "sites": 2,
            "prevalence": 0.0000155,
            "cnames": [
                {
                    "original": "media.newscentermaine.com",
                    "resolved": "media.newscentermaine.com.edgekey.net"
                }
            ],
            "responseHashes": [
                "f4304622914f5add12bf6ec6fda92bed95b080b16906ba7bdc033dd7be2a57f3"
            ],
            "type": "Image",
            "firstPartyCookies": {},
            "firstPartyCookiesSent": {},
            "exampleSites": [
                "newscentermaine.com",
                "www.newscentermaine.com"
            ]
        }
    ],
    "categories": [],
    "performance": {},
    "cookies": 0,
    "types": {
        "Image": 8
    },
    "nameservers": []
}