{
    "domain": "otcmarkets.com.edgekey.net",
    "owner": {
        "name": "Akamai Technologies",
        "displayName": "Akamai",
        "privacyPolicy": "https://www.akamai.com/us/en/privacy-policies/",
        "url": "http://akamai.com"
    },
    "source": [
        "DuckDuckGo-US"
    ],
    "prevalence": 0.0000136,
    "sites": 2,
    "subdomains": [
        "backend"
    ],
    "cnames": [
        {
            "original": "backend.otcmarkets.com",
            "resolved": "backend.otcmarkets.com.edgekey.net"
        }
    ],
    "fingerprinting": 0,
    "resources": [
        {
            "rule": "otcmarkets\\.com\\.edgekey\\.net\\/api\\/v1\\/pages\\/hierarchy",
            "cookies": 0.0000136,
            "fingerprinting": 0,
            "subdomains": [
                "backend"
            ],
            "apis": {},
            "sites": 2,
            "prevalence": 0.0000136,
            "cnames": [
                {
                    "original": "backend.otcmarkets.com",
                    "resolved": "backend.otcmarkets.com.edgekey.net"
                }
            ],
            "responseHashes": [
                "7c24406c3053f3ae8ad8a31feae6bfbcfed7f9cae635b3da8e07e42d438546f2"
            ],
            "type": "XHR",
            "firstPartyCookies": {},
            "firstPartyCookiesSent": {},
            "exampleSites": [
                "otcmarkets.com",
                "www.otcmarkets.com"
            ]
        },
        {
            "rule": "otcmarkets\\.com\\.edgekey\\.net\\/otcapi\\/market-data\\/market-totals",
            "cookies": 0.0000136,
            "fingerprinting": 0,
            "subdomains": [
                "backend"
            ],
            "apis": {},
            "sites": 2,
            "prevalence": 0.0000136,
            "cnames": [
                {
                    "original": "backend.otcmarkets.com",
                    "resolved": "backend.otcmarkets.com.edgekey.net"
                }
            ],
            "responseHashes": [
                "742b3170e6a3511ad135866aab618c7892888f26f5fcd3ae2f9a19472a34d2b6"
            ],
            "type": "XHR",
            "firstPartyCookies": {},
            "firstPartyCookiesSent": {},
            "exampleSites": [
                "otcmarkets.com",
                "www.otcmarkets.com"
            ]
        },
        {
            "rule": "otcmarkets\\.com\\.edgekey\\.net\\/api\\/v1\\/pages\\/path",
            "cookies": 0.0000136,
            "fingerprinting": 0,
            "subdomains": [
                "backend"
            ],
            "apis": {},
            "sites": 2,
            "prevalence": 0.0000136,
            "cnames": [
                {
                    "original": "backend.otcmarkets.com",
                    "resolved": "backend.otcmarkets.com.edgekey.net"
                }
            ],
            "responseHashes": [
                "30fe46ef42873fdaf6640763526f6498b81c127989f3b558f3c2aeaa65e14147"
            ],
            "type": "XHR",
            "firstPartyCookies": {},
            "firstPartyCookiesSent": {},
            "exampleSites": [
                "otcmarkets.com",
                "www.otcmarkets.com"
            ]
        },
        {
            "rule": "otcmarkets\\.com\\.edgekey\\.net\\/otcapi\\/stock\\/trade\\/inside\\/OTCM",
            "cookies": 0.0000136,
            "fingerprinting": 0,
            "subdomains": [
                "backend"
            ],
            "apis": {},
            "sites": 2,
            "prevalence": 0.0000136,
            "cnames": [
                {
                    "original": "backend.otcmarkets.com",
                    "resolved": "backend.otcmarkets.com.edgekey.net"
                }
            ],
            "responseHashes": [
                "9d1ea202a3f851b0771c08db1000749a47444ee8ce8cc7f10a50bbd9c1ea9872"
            ],
            "type": "XHR",
            "firstPartyCookies": {},
            "firstPartyCookiesSent": {},
            "exampleSites": [
                "otcmarkets.com",
                "www.otcmarkets.com"
            ]
        },
        {
            "rule": "otcmarkets\\.com\\.edgekey\\.net\\/otcapi\\/market-data\\/advancers\\/current",
            "cookies": 0.0000136,
            "fingerprinting": 0,
            "subdomains": [
                "backend"
            ],
            "apis": {},
            "sites": 2,
            "prevalence": 0.0000136,
            "cnames": [
                {
                    "original": "backend.otcmarkets.com",
                    "resolved": "backend.otcmarkets.com.edgekey.net"
                }
            ],
            "responseHashes": [
                "ef0442eeb61af6259e67d62cb4ab9613fe7a1279d942a8396b4f513a02359368"
            ],
            "type": "XHR",
            "firstPartyCookies": {},
            "firstPartyCookiesSent": {},
            "exampleSites": [
                "otcmarkets.com",
                "www.otcmarkets.com"
            ]
        },
        {
            "rule": "otcmarkets\\.com\\.edgekey\\.net\\/otcapi\\/company\\/media",
            "cookies": 0.0000136,
            "fingerprinting": 0,
            "subdomains": [
                "backend"
            ],
            "apis": {},
            "sites": 2,
            "prevalence": 0.0000136,
            "cnames": [
                {
                    "original": "backend.otcmarkets.com",
                    "resolved": "backend.otcmarkets.com.edgekey.net"
                }
            ],
            "responseHashes": [
                "5057a1a729bfdb570e79d93f435599a0e261ea4fca895351cfadf4835926ce6f"
            ],
            "type": "XHR",
            "firstPartyCookies": {},
            "firstPartyCookiesSent": {},
            "exampleSites": [
                "otcmarkets.com",
                "www.otcmarkets.com"
            ]
        }
    ],
    "categories": [],
    "performance": {},
    "cookies": 0.0000136,
    "types": {
        "XHR": 12
    },
    "nameservers": []
}