{
    "domain": "redeszone.net",
    "owner": {
        "name": "FISIOZONE SL",
        "displayName": "FISIOZONE"
    },
    "source": [
        "DuckDuckGo-US"
    ],
    "prevalence": 0.0000203,
    "sites": 3,
    "subdomains": [
        "www"
    ],
    "cnames": [],
    "fingerprinting": 0,
    "resources": [
        {
            "rule": "redeszone\\.net\\/app\\/uploads-redeszone\\.net\\/2022\\/09\\/empezar-domotizar-casa\\.jpg",
            "cookies": 0,
            "fingerprinting": 0,
            "subdomains": [
                "www"
            ],
            "apis": {},
            "sites": 2,
            "prevalence": 0.0000135,
            "cnames": [],
            "responseHashes": [
                "ac4dd50043aa9de6fa8dfd442390ffd1f135c7c5c676e86bc0bc7f3a2cfce65c"
            ],
            "type": "Image",
            "firstPartyCookies": {},
            "firstPartyCookiesSent": {},
            "exampleSites": [
                "gearrice.com",
                "www.gearrice.com"
            ]
        }
    ],
    "categories": [],
    "performance": {},
    "cookies": 0,
    "topInitiators": [
        {
            "domain": "first party",
            "prevalence": 1
        }
    ],
    "types": {
        "Image": 2
    },
    "nameservers": [
        "ns2.zilore.net",
        "ns1.zilore.net"
    ]
}